{"2022-01-17":[{"name":"Banker","id":"banker","dns":101,"web":152,"email":74,"total":327,"hosts":[{"name":"alemssparbank.se","dns":1,"web":2,"email":2,"total":5,"rank":21},{"name":"aseochvisteharadssparbank.se","dns":1,"web":1,"email":0,"total":2,"rank":84},{"name":"atvidabergsspb.se","dns":1,"web":2,"email":0,"total":3,"rank":40},{"name":"avanza.se","dns":1,"web":-1,"email":3,"total":3,"rank":32},{"name":"bankgirot.se","dns":2,"web":2,"email":1,"total":5,"rank":13},{"name":"bankomat.se","dns":2,"web":0,"email":1,"total":3,"rank":44},{"name":"bergslagenssparbank.se","dns":1,"web":2,"email":0,"total":3,"rank":65},{"name":"bjursassparbank.se","dns":1,"web":2,"email":0,"total":3,"rank":70},{"name":"bluestep.se","dns":1,"web":0,"email":3,"total":4,"rank":29},{"name":"carnegie.se","dns":1,"web":3,"email":2,"total":6,"rank":4},{"name":"collector.se","dns":1,"web":1,"email":3,"total":5,"rank":11},{"name":"coop.se","dns":1,"web":5,"email":3,"total":9,"rank":1},{"name":"dalsbank.se","dns":1,"web":2,"email":2,"total":5,"rank":14},{"name":"danskebank.se","dns":2,"web":0,"email":1,"total":3,"rank":71},{"name":"dnb.se","dns":2,"web":2,"email":1,"total":5,"rank":20},{"name":"ekebysparbank.se","dns":1,"web":2,"email":0,"total":3,"rank":33},{"name":"ekobanken.se","dns":1,"web":-1,"email":2,"total":2,"rank":85},{"name":"enablebanking.com","dns":1,"web":3,"email":-1,"total":3,"rank":36},{"name":"falkenbergssparbank.se","dns":1,"web":2,"email":0,"total":3,"rank":37},{"name":"forex.se","dns":1,"web":1,"email":-1,"total":1,"rank":90},{"name":"fryksdalenssparbank.se","dns":-2,"web":2,"email":0,"total":0,"rank":92},{"name":"gccab.com","dns":-2,"web":-3,"email":2,"total":-3,"rank":94},{"name":"halsinglandssparbank.se","dns":1,"web":2,"email":0,"total":3,"rank":38},{"name":"handelsbanken.se","dns":2,"web":2,"email":4,"total":8,"rank":2},{"name":"haradssparbanken.se","dns":1,"web":2,"email":0,"total":3,"rank":41},{"name":"hogsbysparbank.se","dns":1,"web":2,"email":0,"total":3,"rank":43},{"name":"icabanken.se","dns":1,"web":2,"email":2,"total":5,"rank":22},{"name":"ikanobank.se","dns":1,"web":-2,"email":-3,"total":-4,"rank":95},{"name":"ivetoftasparbank.se","dns":1,"web":2,"email":0,"total":3,"rank":52},{"name":"jak.se","dns":0,"web":1,"email":2,"total":3,"rank":54},{"name":"kindaydresparbank.se","dns":1,"web":2,"email":0,"total":3,"rank":64},{"name":"klarna.com","dns":1,"web":3,"email":1,"total":5,"rank":23},{"name":"laholmssparbank.se","dns":1,"web":2,"email":0,"total":3,"rank":67},{"name":"landshypotek.se","dns":2,"web":3,"email":3,"total":8,"rank":3},{"name":"lansforsakringar.se","dns":2,"web":2,"email":0,"total":4,"rank":28},{"name":"lekebergssparbank.se","dns":1,"web":2,"email":0,"total":3,"rank":73},{"name":"leksandssparbank.se","dns":1,"web":2,"email":0,"total":3,"rank":78},{"name":"ltvsparbank.se","dns":1,"web":2,"email":2,"total":5,"rank":12},{"name":"marginalen.se","dns":2,"web":1,"email":3,"total":6,"rank":5},{"name":"markarydssparbank.se","dns":1,"web":2,"email":0,"total":3,"rank":34},{"name":"mjobackssparbank.se","dns":1,"web":2,"email":0,"total":3,"rank":35},{"name":"nordax.se","dns":1,"web":3,"email":2,"total":6,"rank":6},{"name":"nordea.se","dns":1,"web":2,"email":1,"total":4,"rank":31},{"name":"nordnet.se","dns":1,"web":2,"email":2,"total":5,"rank":15},{"name":"norrbarke-sparbank.se","dns":1,"web":2,"email":0,"total":3,"rank":39},{"name":"northmill.com","dns":1,"web":1,"email":3,"total":5,"rank":16},{"name":"okq8.se","dns":1,"web":1,"email":2,"total":4,"rank":30},{"name":"olandsbank.se","dns":1,"web":2,"email":0,"total":3,"rank":42},{"name":"orustsparbank.se","dns":1,"web":2,"email":2,"total":5,"rank":17},{"name":"penser.se","dns":1,"web":4,"email":-1,"total":4,"rank":27},{"name":"resursbank.se","dns":1,"web":-2,"email":0,"total":-1,"rank":93},{"name":"roslagenssparbank.se","dns":1,"web":2,"email":0,"total":3,"rank":45},{"name":"salasparbank.se","dns":1,"web":2,"email":0,"total":3,"rank":46},{"name":"sbab.se","dns":0,"web":2,"email":1,"total":3,"rank":47},{"name":"seb.se","dns":2,"web":0,"email":0,"total":2,"rank":87},{"name":"sidensjosparbank.se","dns":1,"web":2,"email":0,"total":3,"rank":48},{"name":"skandia.se","dns":2,"web":-4,"email":3,"total":1,"rank":89},{"name":"skurupssparbank.se","dns":1,"web":2,"email":0,"total":3,"rank":49},{"name":"smsparbank.se","dns":1,"web":2,"email":0,"total":3,"rank":50},{"name":"snapphanebygdenssparbank.se","dns":1,"web":2,"email":0,"total":3,"rank":51},{"name":"sodradalarnassparbank.se","dns":1,"web":2,"email":2,"total":5,"rank":18},{"name":"sodrahestrasparbank.se","dns":1,"web":2,"email":0,"total":3,"rank":53},{"name":"sormlandssparbank.se","dns":1,"web":2,"email":2,"total":5,"rank":19},{"name":"sparbankenalingsas.se","dns":1,"web":2,"email":0,"total":3,"rank":55},{"name":"sparbankenboken.se","dns":1,"web":2,"email":0,"total":3,"rank":56},{"name":"sparbankeneken.se","dns":1,"web":2,"email":0,"total":3,"rank":57},{"name":"sparbankenenkoping.se","dns":1,"web":2,"email":0,"total":3,"rank":58},{"name":"sparbankengoinge.se","dns":1,"web":2,"email":0,"total":3,"rank":59},{"name":"sparbankengotland.se","dns":1,"web":2,"email":0,"total":3,"rank":60},{"name":"sparbankenikarlshamn.se","dns":1,"web":2,"email":0,"total":3,"rank":61},{"name":"sparbankenlidkoping.se","dns":1,"web":2,"email":0,"total":3,"rank":62},{"name":"sparbankennord.se","dns":1,"web":-1,"email":0,"total":0,"rank":91},{"name":"sparbankenrekarne.se","dns":1,"web":2,"email":0,"total":3,"rank":63},{"name":"sparbankensjuharad.se","dns":2,"web":2,"email":2,"total":6,"rank":7},{"name":"sparbankenskane.se","dns":1,"web":2,"email":3,"total":6,"rank":8},{"name":"sparbankenskaraborg.se","dns":1,"web":2,"email":0,"total":3,"rank":66},{"name":"sparbankensyd.se","dns":1,"web":3,"email":2,"total":6,"rank":9},{"name":"sparbankentanum.se","dns":1,"web":2,"email":0,"total":3,"rank":68},{"name":"sparbankentranemo.se","dns":1,"web":2,"email":0,"total":3,"rank":69},{"name":"sparbankenvm.se","dns":2,"web":2,"email":2,"total":6,"rank":10},{"name":"svea.com","dns":1,"web":2,"email":2,"total":5,"rank":24},{"name":"swedbank.se","dns":1,"web":0,"email":2,"total":3,"rank":72},{"name":"tfbank.se","dns":2,"web":3,"email":0,"total":5,"rank":25},{"name":"tidaholms-sparbank.se","dns":1,"web":2,"email":0,"total":3,"rank":74},{"name":"tjorns-sparbank.se","dns":1,"web":2,"email":0,"total":3,"rank":75},{"name":"tjustbanken.se","dns":1,"web":2,"email":0,"total":3,"rank":76},{"name":"ulricehamnssparbank.se","dns":1,"web":2,"email":0,"total":3,"rank":77},{"name":"vadstenasparbank.se","dns":1,"web":2,"email":2,"total":5,"rank":26},{"name":"valdemarsvikssparbank.se","dns":1,"web":2,"email":0,"total":3,"rank":79},{"name":"varbergssparbank.se","dns":1,"web":2,"email":0,"total":3,"rank":80},{"name":"vimmerbysparbank.se","dns":1,"web":2,"email":0,"total":3,"rank":81},{"name":"virserumssparbank.se","dns":1,"web":2,"email":0,"total":3,"rank":82},{"name":"volvofinans.se","dns":2,"web":-1,"email":1,"total":2,"rank":86},{"name":"wwsparbank.se","dns":1,"web":2,"email":0,"total":3,"rank":83},{"name":"ölandsbank.se","dns":1,"web":0,"email":1,"total":2,"rank":88}],"rank":6},{"name":"Dagstidningar","id":"dagstidningar","dns":30,"web":152,"email":60,"total":242,"hosts":[{"name":"aftonbladet.se","dns":1,"web":2,"email":3,"total":6,"rank":11},{"name":"allehanda.se","dns":-2,"web":3,"email":0,"total":1,"rank":56},{"name":"arbetarbladet.se","dns":-2,"web":3,"email":0,"total":1,"rank":55},{"name":"barometern.se","dns":1,"web":3,"email":2,"total":6,"rank":5},{"name":"blt.se","dns":1,"web":3,"email":2,"total":6,"rank":6},{"name":"corren.se","dns":1,"web":1,"email":2,"total":4,"rank":39},{"name":"dagen.se","dns":1,"web":4,"email":2,"total":7,"rank":1},{"name":"dagenssamhalle.se","dns":1,"web":2,"email":1,"total":4,"rank":47},{"name":"dalademokraten.se","dns":-2,"web":3,"email":0,"total":1,"rank":61},{"name":"di.se","dns":1,"web":3,"email":0,"total":4,"rank":23},{"name":"dn.se","dns":1,"web":1,"email":0,"total":2,"rank":50},{"name":"dt.se","dns":-2,"web":3,"email":0,"total":1,"rank":57},{"name":"ekuriren.se","dns":1,"web":1,"email":2,"total":4,"rank":31},{"name":"eposten.se","dns":1,"web":1,"email":2,"total":4,"rank":34},{"name":"expressen.se","dns":1,"web":2,"email":0,"total":3,"rank":49},{"name":"falukuriren.se","dns":-2,"web":0,"email":0,"total":-2,"rank":64},{"name":"folkbladet.nu","dns":1,"web":2,"email":2,"total":5,"rank":20},{"name":"folket.se","dns":1,"web":-2,"email":0,"total":-1,"rank":62},{"name":"gd.se","dns":-2,"web":3,"email":0,"total":1,"rank":59},{"name":"gp.se","dns":2,"web":3,"email":0,"total":5,"rank":15},{"name":"hallandsposten.se","dns":2,"web":3,"email":0,"total":5,"rank":17},{"name":"hallekis.com","dns":2,"web":3,"email":2,"total":7,"rank":2},{"name":"hd.se","dns":1,"web":6,"email":0,"total":7,"rank":3},{"name":"helagotland.se","dns":1,"web":1,"email":2,"total":4,"rank":35},{"name":"helahalsingland.se","dns":-2,"web":3,"email":0,"total":1,"rank":60},{"name":"hn.se","dns":2,"web":3,"email":0,"total":5,"rank":16},{"name":"ht.se","dns":-2,"web":0,"email":0,"total":-2,"rank":63},{"name":"jnytt.se","dns":1,"web":3,"email":0,"total":4,"rank":40},{"name":"jp.se","dns":1,"web":3,"email":0,"total":4,"rank":41},{"name":"kkuriren.se","dns":1,"web":1,"email":2,"total":4,"rank":43},{"name":"kristianstadsbladet.se","dns":1,"web":3,"email":2,"total":6,"rank":7},{"name":"kuriren.nu","dns":1,"web":1,"email":2,"total":4,"rank":21},{"name":"lt.se","dns":1,"web":3,"email":0,"total":4,"rank":22},{"name":"ltz.se","dns":-2,"web":3,"email":0,"total":1,"rank":54},{"name":"metromode.se","dns":1,"web":3,"email":1,"total":5,"rank":19},{"name":"mvt.se","dns":1,"web":1,"email":2,"total":4,"rank":24},{"name":"na.se","dns":1,"web":3,"email":0,"total":4,"rank":25},{"name":"norran.se","dns":1,"web":1,"email":2,"total":4,"rank":26},{"name":"norrteljetidning.se","dns":1,"web":3,"email":0,"total":4,"rank":27},{"name":"nsd.se","dns":1,"web":1,"email":2,"total":4,"rank":28},{"name":"nt.se","dns":1,"web":1,"email":2,"total":4,"rank":29},{"name":"nwt.se","dns":-2,"web":4,"email":0,"total":2,"rank":53},{"name":"nynashamnsposten.se","dns":1,"web":3,"email":0,"total":4,"rank":30},{"name":"olandsbladet.se","dns":1,"web":3,"email":2,"total":6,"rank":8},{"name":"op.se","dns":-2,"web":3,"email":0,"total":1,"rank":58},{"name":"pt.se","dns":1,"web":1,"email":2,"total":4,"rank":32},{"name":"salaallehanda.com","dns":1,"web":3,"email":0,"total":4,"rank":33},{"name":"skd.se","dns":1,"web":4,"email":0,"total":5,"rank":14},{"name":"sla.se","dns":-2,"web":4,"email":0,"total":2,"rank":51},{"name":"smp.se","dns":1,"web":3,"email":2,"total":6,"rank":9},{"name":"sn.se","dns":1,"web":1,"email":2,"total":4,"rank":36},{"name":"st.nu","dns":1,"web":3,"email":0,"total":4,"rank":37},{"name":"svd.se","dns":1,"web":0,"email":3,"total":4,"rank":38},{"name":"sydostran.se","dns":1,"web":3,"email":2,"total":6,"rank":10},{"name":"sydsvenskan.se","dns":1,"web":6,"email":0,"total":7,"rank":4},{"name":"ttela.se","dns":2,"web":3,"email":0,"total":5,"rank":18},{"name":"unt.se","dns":1,"web":1,"email":2,"total":4,"rank":42},{"name":"ut.se","dns":1,"web":3,"email":2,"total":6,"rank":12},{"name":"vf.se","dns":-2,"web":4,"email":0,"total":2,"rank":52},{"name":"vimmerbytidning.se","dns":1,"web":1,"email":2,"total":4,"rank":44},{"name":"vk.se","dns":1,"web":2,"email":0,"total":3,"rank":48},{"name":"vlt.se","dns":1,"web":3,"email":0,"total":4,"rank":45},{"name":"vt.se","dns":1,"web":1,"email":2,"total":4,"rank":46},{"name":"ystadsallehanda.se","dns":1,"web":3,"email":2,"total":6,"rank":13}],"rank":3},{"name":"Försäkringsbolag","id":"frskringsbolag","dns":34,"web":46,"email":33,"total":113,"hosts":[{"name":"accept.se","dns":2,"web":3,"email":0,"total":5,"rank":11},{"name":"agria.se","dns":-2,"web":-2,"email":0,"total":-4,"rank":30},{"name":"aktsam.se","dns":1,"web":1,"email":0,"total":2,"rank":25},{"name":"alandia.se","dns":1,"web":2,"email":2,"total":5,"rank":10},{"name":"atlantica.se","dns":1,"web":1,"email":2,"total":4,"rank":13},{"name":"bliwa.se","dns":1,"web":4,"email":2,"total":7,"rank":1},{"name":"dina.se","dns":1,"web":2,"email":0,"total":3,"rank":20},{"name":"erv.se","dns":1,"web":3,"email":2,"total":6,"rank":6},{"name":"folksam.se","dns":1,"web":4,"email":2,"total":7,"rank":2},{"name":"gjensidige.se","dns":2,"web":-1,"email":2,"total":3,"rank":21},{"name":"gouda-rf.se","dns":2,"web":2,"email":2,"total":6,"rank":7},{"name":"helaforsakring.se","dns":1,"web":3,"email":2,"total":6,"rank":9},{"name":"icaforsakring.se","dns":1,"web":1,"email":0,"total":2,"rank":24},{"name":"idunliv.se","dns":0,"web":1,"email":2,"total":3,"rank":23},{"name":"if.se","dns":1,"web":3,"email":3,"total":7,"rank":3},{"name":"insurify.se","dns":1,"web":1,"email":2,"total":4,"rank":15},{"name":"lansforsakringar.se","dns":2,"web":2,"email":0,"total":4,"rank":18},{"name":"modernaforsakringar.se","dns":1,"web":1,"email":2,"total":4,"rank":12},{"name":"movestic.se","dns":1,"web":4,"email":2,"total":7,"rank":4},{"name":"paydrive.se","dns":2,"web":0,"email":-3,"total":-1,"rank":29},{"name":"protectorforsakring.se","dns":2,"web":-1,"email":2,"total":3,"rank":22},{"name":"skandia.se","dns":2,"web":-4,"email":3,"total":1,"rank":26},{"name":"solidab.se","dns":1,"web":0,"email":0,"total":1,"rank":27},{"name":"svedea.se","dns":1,"web":4,"email":-1,"total":4,"rank":14},{"name":"sveland.se","dns":0,"web":3,"email":-3,"total":0,"rank":28},{"name":"swedbank.se","dns":1,"web":0,"email":2,"total":3,"rank":19},{"name":"trygghansa.se","dns":1,"web":5,"email":0,"total":6,"rank":8},{"name":"vardia.se","dns":2,"web":0,"email":2,"total":4,"rank":16},{"name":"villaagarna.se","dns":1,"web":1,"email":2,"total":4,"rank":17},{"name":"watercircles.se","dns":2,"web":3,"email":2,"total":7,"rank":5}],"rank":4},{"name":"ISPer","id":"isper","dns":143,"web":257,"email":81,"total":481,"hosts":[{"name":"1access.se","dns":1,"web":1,"email":2,"total":4,"rank":52},{"name":"31173.se","dns":1,"web":-3,"email":0,"total":-2,"rank":151},{"name":"84grams.se","dns":2,"web":3,"email":2,"total":7,"rank":11},{"name":"a3foretag.se","dns":1,"web":1,"email":0,"total":2,"rank":99},{"name":"aktivit.se","dns":1,"web":5,"email":-1,"total":5,"rank":49},{"name":"alltele.se","dns":1,"web":1,"email":2,"total":4,"rank":55},{"name":"alvsbyn.se","dns":2,"web":4,"email":-3,"total":3,"rank":95},{"name":"ansluten.net","dns":1,"web":3,"email":2,"total":6,"rank":21},{"name":"arkaden.se","dns":1,"web":2,"email":2,"total":5,"rank":47},{"name":"asele.se","dns":-1,"web":3,"email":2,"total":4,"rank":65},{"name":"awiwo.com","dns":1,"web":3,"email":2,"total":6,"rank":27},{"name":"b2b.medianetwork.se","dns":1,"web":1,"email":-2,"total":0,"rank":137},{"name":"bahnhof.se","dns":1,"web":4,"email":2,"total":7,"rank":16},{"name":"bik.nu","dns":1,"web":3,"email":0,"total":4,"rank":61},{"name":"bjarekraft.se","dns":1,"web":4,"email":2,"total":7,"rank":7},{"name":"bjurholm.se","dns":1,"web":2,"email":-1,"total":2,"rank":100},{"name":"bktv.se","dns":-2,"web":3,"email":-2,"total":-1,"rank":145},{"name":"bluerange.se","dns":1,"web":3,"email":2,"total":6,"rank":28},{"name":"bollnasenergi.se","dns":1,"web":3,"email":2,"total":6,"rank":29},{"name":"borenet.se","dns":1,"web":-2,"email":0,"total":-1,"rank":147},{"name":"boxer.se","dns":1,"web":-1,"email":2,"total":2,"rank":115},{"name":"bredband2.com","dns":2,"web":3,"email":-1,"total":4,"rank":59},{"name":"bredbandsson.se","dns":-2,"web":1,"email":0,"total":-1,"rank":148},{"name":"bredbandsteknik.se","dns":-2,"web":3,"email":0,"total":1,"rank":123},{"name":"bredbandstjanster.se","dns":-2,"web":1,"email":-1,"total":-2,"rank":150},{"name":"carlslid.se","dns":1,"web":3,"email":-3,"total":1,"rank":133},{"name":"colt.net","dns":1,"web":3,"email":2,"total":6,"rank":19},{"name":"comhem.se","dns":1,"web":1,"email":-1,"total":1,"rank":130},{"name":"connectel.io","dns":1,"web":3,"email":2,"total":6,"rank":20},{"name":"connect.se","dns":0,"web":1,"email":3,"total":4,"rank":73},{"name":"daladatorer.se","dns":1,"web":3,"email":0,"total":4,"rank":79},{"name":"dalakraft.se","dns":0,"web":0,"email":2,"total":2,"rank":103},{"name":"datacom.se","dns":1,"web":1,"email":0,"total":2,"rank":104},{"name":"dgc.se","dns":1,"web":0,"email":-2,"total":-1,"rank":143},{"name":"doffdata.se","dns":1,"web":-1,"email":2,"total":2,"rank":107},{"name":"dorotea.se","dns":2,"web":1,"email":-1,"total":2,"rank":111},{"name":"egonet.se","dns":1,"web":0,"email":-1,"total":0,"rank":135},{"name":"eidsiva.net","dns":1,"web":3,"email":-2,"total":2,"rank":114},{"name":"eksjoenergi.se","dns":2,"web":3,"email":3,"total":8,"rank":3},{"name":"ember.se","dns":1,"web":1,"email":-1,"total":1,"rank":132},{"name":"epm.se","dns":1,"web":1,"email":0,"total":2,"rank":116},{"name":"excedo.se","dns":2,"web":3,"email":1,"total":6,"rank":25},{"name":"excellent-hosting.se","dns":-1,"web":0,"email":2,"total":1,"rank":124},{"name":"fastbit.se","dns":2,"web":3,"email":0,"total":5,"rank":40},{"name":"fiberstaden.se","dns":2,"web":3,"email":0,"total":5,"rank":46},{"name":"finet.se","dns":1,"web":3,"email":-1,"total":3,"rank":85},{"name":"forss.se","dns":1,"web":1,"email":-1,"total":1,"rank":118},{"name":"fouredge.se","dns":1,"web":3,"email":0,"total":4,"rank":62},{"name":"gamma.co.uk","dns":1,"web":5,"email":2,"total":8,"rank":2},{"name":"gastabudstaden.se","dns":1,"web":3,"email":-1,"total":3,"rank":93},{"name":"gavleenergi.se","dns":1,"web":3,"email":0,"total":4,"rank":71},{"name":"glesys.se","dns":1,"web":4,"email":2,"total":7,"rank":6},{"name":"glocalnet.se","dns":1,"web":2,"email":-1,"total":2,"rank":97},{"name":"gotanet.se","dns":2,"web":-2,"email":1,"total":1,"rank":120},{"name":"griffel.se","dns":1,"web":-4,"email":2,"total":-1,"rank":144},{"name":"haboenergi.se","dns":-2,"web":0,"email":2,"total":0,"rank":142},{"name":"habonet.net","dns":1,"web":3,"email":0,"total":4,"rank":74},{"name":"hagnor.se","dns":1,"web":1,"email":2,"total":4,"rank":77},{"name":"haparanda.se","dns":2,"web":4,"email":-3,"total":3,"rank":84},{"name":"hebynet.se","dns":1,"web":3,"email":1,"total":5,"rank":35},{"name":"helsingenetovanaker.se","dns":1,"web":0,"email":-3,"total":-2,"rank":155},{"name":"hjoenergi.se","dns":0,"web":3,"email":0,"total":3,"rank":88},{"name":"hogsbynat.se","dns":-2,"web":1,"email":2,"total":1,"rank":117},{"name":"ide.resurscentrum.se","dns":1,"web":-1,"email":2,"total":2,"rank":109},{"name":"imegasystem.se","dns":1,"web":3,"email":-3,"total":1,"rank":119},{"name":"indicate.se","dns":1,"web":1,"email":2,"total":4,"rank":50},{"name":"infracomgroup.se","dns":1,"web":1,"email":2,"total":4,"rank":51},{"name":"interlan.se","dns":2,"web":4,"email":3,"total":9,"rank":1},{"name":"internetport.se","dns":2,"web":3,"email":-1,"total":4,"rank":53},{"name":"ip-only.se","dns":1,"web":1,"email":-1,"total":1,"rank":131},{"name":"ip-osteraker.se","dns":1,"web":1,"email":1,"total":3,"rank":87},{"name":"ipsweden.se","dns":-2,"web":1,"email":-3,"total":-4,"rank":160},{"name":"it4u.se","dns":2,"web":3,"email":0,"total":5,"rank":42},{"name":"it-centrum.se","dns":2,"web":0,"email":3,"total":5,"rank":43},{"name":"itofsweden.se","dns":1,"web":3,"email":2,"total":6,"rank":30},{"name":"itsystem.se","dns":1,"web":4,"email":-2,"total":3,"rank":83},{"name":"jarfallaonline.se","dns":0,"web":0,"email":2,"total":2,"rank":105},{"name":"j-fab.net","dns":1,"web":0,"email":-1,"total":0,"rank":136},{"name":"jordberga.se","dns":2,"web":-2,"email":1,"total":1,"rank":121},{"name":"junet.se","dns":1,"web":-3,"email":2,"total":0,"rank":138},{"name":"karlsborgsenergi.se","dns":1,"web":3,"email":2,"total":6,"rank":32},{"name":"karlskogaenergi.se","dns":1,"web":1,"email":0,"total":2,"rank":108},{"name":"knivstanet.se","dns":1,"web":3,"email":0,"total":4,"rank":64},{"name":"koping.net","dns":1,"web":4,"email":-3,"total":2,"rank":110},{"name":"kungalvenergi.se","dns":1,"web":3,"email":2,"total":6,"rank":33},{"name":"kustbandet.com","dns":1,"web":0,"email":-1,"total":0,"rank":139},{"name":"lacable.se","dns":1,"web":3,"email":0,"total":4,"rank":67},{"name":"layermesh.se","dns":2,"web":3,"email":-1,"total":4,"rank":68},{"name":"lidendata.se","dns":1,"web":3,"email":0,"total":4,"rank":69},{"name":"lidnet.se","dns":1,"web":3,"email":0,"total":4,"rank":70},{"name":"ljusdalenergi.se","dns":1,"web":1,"email":0,"total":2,"rank":98},{"name":"lyssna-njut.se","dns":1,"web":3,"email":2,"total":6,"rank":34},{"name":"mdfnet.se","dns":-1,"web":0,"email":-1,"total":-2,"rank":149},{"name":"mediateknik.com","dns":1,"web":4,"email":0,"total":5,"rank":36},{"name":"mediateknik.net","dns":1,"web":3,"email":-1,"total":3,"rank":86},{"name":"microgroup.se","dns":1,"web":0,"email":0,"total":1,"rank":125},{"name":"microtec.se","dns":-2,"web":1,"email":2,"total":1,"rank":127},{"name":"minitel.se","dns":2,"web":0,"email":3,"total":5,"rank":38},{"name":"n62.se","dns":1,"web":4,"email":2,"total":7,"rank":8},{"name":"nentgroup.com","dns":1,"web":-1,"email":0,"total":0,"rank":141},{"name":"netatonce.se","dns":1,"web":3,"email":0,"total":4,"rank":78},{"name":"netnod.se","dns":2,"web":1,"email":2,"total":5,"rank":41},{"name":"nordlo.com","dns":1,"web":3,"email":3,"total":7,"rank":9},{"name":"norsjobredband.se","dns":2,"web":3,"email":2,"total":7,"rank":10},{"name":"nossebroenergi.se","dns":1,"web":3,"email":2,"total":6,"rank":22},{"name":"obenetwork.com","dns":1,"web":3,"email":2,"total":6,"rank":23},{"name":"oktv.se","dns":-2,"web":-4,"email":0,"total":-6,"rank":163},{"name":"on1call.se","dns":1,"web":-3,"email":2,"total":0,"rank":140},{"name":"oretel.se","dns":1,"web":1,"email":2,"total":4,"rank":54},{"name":"osterlenskraft.se","dns":1,"web":3,"email":2,"total":6,"rank":24},{"name":"oversite.se","dns":-2,"web":4,"email":2,"total":4,"rank":56},{"name":"ownit.se","dns":1,"web":3,"email":0,"total":4,"rank":57},{"name":"perspektivbredband.se","dns":1,"web":-2,"email":-2,"total":-3,"rank":158},{"name":"phonera.se","dns":1,"web":-2,"email":2,"total":1,"rank":126},{"name":"primlight.net","dns":1,"web":-3,"email":-1,"total":-3,"rank":156},{"name":"qavat.se","dns":1,"web":-3,"email":-1,"total":-3,"rank":157},{"name":"qos.se","dns":1,"web":3,"email":-1,"total":3,"rank":80},{"name":"quicknet.se","dns":1,"web":0,"email":0,"total":1,"rank":128},{"name":"rbcom.se","dns":1,"web":-2,"email":0,"total":-1,"rank":146},{"name":"sandvikenenergi.se","dns":2,"web":1,"email":0,"total":3,"rank":81},{"name":"sappa.se","dns":1,"web":1,"email":0,"total":2,"rank":102},{"name":"savman.se","dns":1,"web":3,"email":-1,"total":3,"rank":82},{"name":"servanet.se","dns":1,"web":3,"email":0,"total":4,"rank":58},{"name":"soderhamnnara.se","dns":2,"web":4,"email":2,"total":8,"rank":4},{"name":"springmobil.se","dns":1,"web":0,"email":1,"total":2,"rank":106},{"name":"stockholmsstadsnat.se","dns":2,"web":3,"email":-1,"total":4,"rank":60},{"name":"straznet.se","dns":1,"web":3,"email":2,"total":6,"rank":26},{"name":"sunet.se","dns":2,"web":1,"email":2,"total":5,"rank":37},{"name":"sverigesbredband.se","dns":-1,"web":3,"email":-1,"total":1,"rank":122},{"name":"swedavia.se","dns":1,"web":3,"email":0,"total":4,"rank":63},{"name":"sydantenn.se","dns":1,"web":0,"email":-1,"total":0,"rank":134},{"name":"t3.se","dns":1,"web":0,"email":2,"total":3,"rank":92},{"name":"tdc.se","dns":2,"web":0,"email":0,"total":2,"rank":112},{"name":"teamfront.se","dns":1,"web":4,"email":2,"total":7,"rank":12},{"name":"teknorama.se","dns":1,"web":0,"email":2,"total":3,"rank":94},{"name":"tele2.se","dns":1,"web":2,"email":2,"total":5,"rank":39},{"name":"teleman.se","dns":1,"web":3,"email":-1,"total":3,"rank":96},{"name":"telenor.se","dns":1,"web":3,"email":0,"total":4,"rank":66},{"name":"teleservice.net","dns":1,"web":4,"email":2,"total":7,"rank":13},{"name":"teletek.se","dns":1,"web":0,"email":-3,"total":-2,"rank":153},{"name":"teliacompany.com","dns":1,"web":4,"email":2,"total":7,"rank":14},{"name":"th1ng.se","dns":1,"web":2,"email":-1,"total":2,"rank":101},{"name":"tibroenergi.se","dns":1,"web":3,"email":3,"total":7,"rank":15},{"name":"tidaholmsenergi.se","dns":1,"web":3,"email":2,"total":6,"rank":31},{"name":"tk-data.se","dns":2,"web":-2,"email":-2,"total":-2,"rank":152},{"name":"top24.se","dns":2,"web":3,"email":0,"total":5,"rank":44},{"name":"tranquillity.se","dns":-1,"web":-1,"email":-2,"total":-4,"rank":162},{"name":"tre.se","dns":-1,"web":2,"email":3,"total":4,"rank":72},{"name":"vaggerydsenergi.se","dns":1,"web":1,"email":3,"total":5,"rank":45},{"name":"vanerenergi.se","dns":1,"web":4,"email":3,"total":8,"rank":5},{"name":"vannas.se","dns":2,"web":2,"email":-1,"total":3,"rank":89},{"name":"varbergenergi.se","dns":2,"web":1,"email":0,"total":3,"rank":90},{"name":"varnamoenergi.se","dns":1,"web":2,"email":0,"total":3,"rank":91},{"name":"verizon.com","dns":1,"web":2,"email":1,"total":4,"rank":75},{"name":"vilhelmina.se","dns":-1,"web":3,"email":2,"total":4,"rank":76},{"name":"virserum.com","dns":-1,"web":0,"email":2,"total":1,"rank":129},{"name":"visolit.se","dns":1,"web":1,"email":0,"total":2,"rank":113},{"name":"voicetech.nu","dns":2,"web":-3,"email":-2,"total":-3,"rank":159},{"name":"vokby.se","dns":0,"web":-6,"email":2,"total":-4,"rank":161},{"name":"wintherwireless.se","dns":2,"web":3,"email":2,"total":7,"rank":17},{"name":"yelles.se","dns":2,"web":3,"email":0,"total":5,"rank":48},{"name":"ymex.se","dns":1,"web":-2,"email":-1,"total":-2,"rank":154},{"name":"zedcom.se","dns":1,"web":4,"email":2,"total":7,"rank":18}],"rank":10},{"name":"Kommuner","id":"kommuner","dns":393,"web":637,"email":181,"total":1211,"hosts":[{"name":"ale.se","dns":1,"web":2,"email":2,"total":5,"rank":117},{"name":"alingsas.se","dns":1,"web":3,"email":0,"total":4,"rank":151},{"name":"almhult.se","dns":2,"web":4,"email":-1,"total":5,"rank":123},{"name":"alvdalen.se","dns":2,"web":4,"email":0,"total":6,"rank":72},{"name":"alvesta.se","dns":2,"web":3,"email":2,"total":7,"rank":32},{"name":"alvkarleby.se","dns":0,"web":-1,"email":0,"total":-1,"rank":335},{"name":"alvsbyn.se","dns":2,"web":4,"email":-3,"total":3,"rank":210},{"name":"amal.se","dns":2,"web":1,"email":-1,"total":2,"rank":233},{"name":"aneby.se","dns":2,"web":1,"email":3,"total":6,"rank":63},{"name":"ange.se","dns":2,"web":4,"email":2,"total":8,"rank":11},{"name":"arboga.se","dns":1,"web":4,"email":-1,"total":4,"rank":155},{"name":"are.se","dns":2,"web":0,"email":2,"total":4,"rank":159},{"name":"arjang.se","dns":0,"web":4,"email":0,"total":4,"rank":168},{"name":"arjeplog.se","dns":2,"web":1,"email":-1,"total":2,"rank":230},{"name":"arvidsjaur.se","dns":2,"web":1,"email":0,"total":3,"rank":194},{"name":"arvika.se","dns":1,"web":2,"email":0,"total":3,"rank":206},{"name":"asele.se","dns":-1,"web":3,"email":2,"total":4,"rank":147},{"name":"askersund.se","dns":0,"web":4,"email":0,"total":4,"rank":149},{"name":"astorp.se","dns":2,"web":4,"email":0,"total":6,"rank":55},{"name":"atvidaberg.se","dns":1,"web":4,"email":2,"total":7,"rank":47},{"name":"avesta.se","dns":2,"web":0,"email":3,"total":5,"rank":97},{"name":"bastad.se","dns":-2,"web":0,"email":0,"total":-2,"rank":338},{"name":"bengtsfors.se","dns":-2,"web":2,"email":2,"total":2,"rank":237},{"name":"berg.se","dns":2,"web":2,"email":-3,"total":1,"rank":270},{"name":"bjurholm.se","dns":1,"web":2,"email":-1,"total":2,"rank":241},{"name":"bjuv.se","dns":1,"web":4,"email":-3,"total":2,"rank":227},{"name":"boden.se","dns":-1,"web":-3,"email":3,"total":-1,"rank":326},{"name":"bollebygd.se","dns":1,"web":4,"email":0,"total":5,"rank":107},{"name":"bollnas.se","dns":2,"web":0,"email":0,"total":2,"rank":231},{"name":"boras.se","dns":2,"web":4,"email":0,"total":6,"rank":68},{"name":"borgholm.se","dns":-1,"web":0,"email":-3,"total":-4,"rank":346},{"name":"borlange.se","dns":2,"web":2,"email":3,"total":7,"rank":22},{"name":"botkyrka.se","dns":0,"web":4,"email":2,"total":6,"rank":88},{"name":"boxholm.se","dns":1,"web":4,"email":2,"total":7,"rank":23},{"name":"bracke.se","dns":0,"web":4,"email":0,"total":4,"rank":156},{"name":"bromolla.se","dns":-2,"web":-2,"email":0,"total":-4,"rank":347},{"name":"burlov.se","dns":1,"web":4,"email":2,"total":7,"rank":31},{"name":"dalsed.se","dns":2,"web":3,"email":3,"total":8,"rank":13},{"name":"danderyd.se","dns":2,"web":0,"email":2,"total":4,"rank":169},{"name":"degerfors.se","dns":1,"web":2,"email":0,"total":3,"rank":200},{"name":"dorotea.se","dns":2,"web":1,"email":-1,"total":2,"rank":250},{"name":"eda.se","dns":2,"web":1,"email":-3,"total":0,"rank":308},{"name":"ekero.se","dns":1,"web":4,"email":-1,"total":4,"rank":139},{"name":"eksjo.se","dns":2,"web":1,"email":3,"total":6,"rank":69},{"name":"emmaboda.se","dns":1,"web":2,"email":0,"total":3,"rank":218},{"name":"engelholm.se","dns":1,"web":2,"email":0,"total":3,"rank":219},{"name":"enkoping.se","dns":2,"web":4,"email":-3,"total":3,"rank":189},{"name":"eskilstuna.se","dns":1,"web":2,"email":2,"total":5,"rank":99},{"name":"eslov.se","dns":2,"web":-1,"email":0,"total":1,"rank":277},{"name":"essunga.se","dns":2,"web":4,"email":1,"total":7,"rank":43},{"name":"fagersta.se","dns":2,"web":4,"email":0,"total":6,"rank":73},{"name":"falkenberg.se","dns":2,"web":1,"email":0,"total":3,"rank":207},{"name":"falkoping.se","dns":2,"web":1,"email":0,"total":3,"rank":208},{"name":"falun.se","dns":2,"web":4,"email":2,"total":8,"rank":14},{"name":"fargelanda.se","dns":-2,"web":3,"email":2,"total":3,"rank":212},{"name":"filipstad.se","dns":2,"web":-1,"email":0,"total":1,"rank":299},{"name":"finspang.se","dns":1,"web":4,"email":0,"total":5,"rank":129},{"name":"flen.se","dns":1,"web":1,"email":2,"total":4,"rank":167},{"name":"forshaga.se","dns":-2,"web":4,"email":0,"total":2,"rank":223},{"name":"gagnef.se","dns":2,"web":1,"email":-1,"total":2,"rank":225},{"name":"gallivare.se","dns":2,"web":-2,"email":0,"total":0,"rank":306},{"name":"gavle.se","dns":2,"web":3,"email":0,"total":5,"rank":131},{"name":"gellivare.se","dns":2,"web":0,"email":-4,"total":-2,"rank":342},{"name":"gislaved.se","dns":2,"web":1,"email":2,"total":5,"rank":136},{"name":"gnesta.se","dns":2,"web":4,"email":2,"total":8,"rank":18},{"name":"gnosjo.se","dns":-2,"web":2,"email":-3,"total":-3,"rank":344},{"name":"goteborg.se","dns":2,"web":4,"email":0,"total":6,"rank":60},{"name":"gotene.se","dns":2,"web":5,"email":1,"total":8,"rank":19},{"name":"gotland.se","dns":2,"web":1,"email":2,"total":5,"rank":108},{"name":"grastorp.se","dns":1,"web":4,"email":1,"total":6,"rank":67},{"name":"grums.se","dns":2,"web":1,"email":2,"total":5,"rank":120},{"name":"gullspang.se","dns":1,"web":4,"email":-2,"total":3,"rank":213},{"name":"habokommun.se","dns":2,"web":4,"email":1,"total":7,"rank":26},{"name":"habo.se","dns":2,"web":4,"email":-1,"total":5,"rank":127},{"name":"hagfors.se","dns":1,"web":4,"email":3,"total":8,"rank":6},{"name":"hallsberg.se","dns":0,"web":4,"email":-1,"total":3,"rank":191},{"name":"hallstahammar.se","dns":2,"web":4,"email":-1,"total":5,"rank":130},{"name":"halmstad.se","dns":2,"web":-2,"email":3,"total":3,"rank":198},{"name":"hammaro.se","dns":2,"web":-2,"email":3,"total":3,"rank":199},{"name":"haninge.se","dns":2,"web":3,"email":-1,"total":4,"rank":186},{"name":"haparanda.se","dns":2,"web":4,"email":-3,"total":3,"rank":205},{"name":"harnosand.se","dns":2,"web":1,"email":1,"total":4,"rank":138},{"name":"harryda.se","dns":2,"web":4,"email":2,"total":8,"rank":7},{"name":"hassleholm.se","dns":1,"web":4,"email":2,"total":7,"rank":34},{"name":"heby.se","dns":1,"web":2,"email":2,"total":5,"rank":95},{"name":"hedemora.se","dns":-1,"web":1,"email":-1,"total":-1,"rank":334},{"name":"hellefors.se","dns":1,"web":4,"email":0,"total":5,"rank":96},{"name":"helsingborg.se","dns":-1,"web":3,"email":2,"total":4,"rank":152},{"name":"herjedalen.se","dns":2,"web":4,"email":0,"total":6,"rank":75},{"name":"herrljunga.se","dns":0,"web":-1,"email":2,"total":1,"rank":288},{"name":"hjo.se","dns":-2,"web":-2,"email":2,"total":-2,"rank":337},{"name":"hofors.se","dns":-1,"web":1,"email":2,"total":2,"rank":222},{"name":"hoganas.se","dns":2,"web":1,"email":2,"total":5,"rank":98},{"name":"hogsby.se","dns":2,"web":1,"email":0,"total":3,"rank":188},{"name":"hoor.se","dns":1,"web":0,"email":0,"total":1,"rank":280},{"name":"horby.se","dns":1,"web":-2,"email":0,"total":-1,"rank":332},{"name":"huddinge.se","dns":1,"web":3,"email":0,"total":4,"rank":158},{"name":"hudiksvall.se","dns":2,"web":4,"email":0,"total":6,"rank":83},{"name":"hultsfred.se","dns":2,"web":0,"email":2,"total":4,"rank":160},{"name":"hylte.se","dns":1,"web":1,"email":-4,"total":-2,"rank":343},{"name":"jarfalla.se","dns":0,"web":4,"email":0,"total":4,"rank":163},{"name":"jokkmokk.se","dns":2,"web":-3,"email":2,"total":1,"rank":278},{"name":"jonkoping.se","dns":-1,"web":-1,"email":0,"total":-2,"rank":341},{"name":"kalix.se","dns":2,"web":0,"email":0,"total":2,"rank":236},{"name":"kalmar.se","dns":2,"web":3,"email":0,"total":5,"rank":100},{"name":"karlsborg.se","dns":-2,"web":1,"email":2,"total":1,"rank":289},{"name":"karlshamn.se","dns":2,"web":3,"email":2,"total":7,"rank":35},{"name":"karlskoga.se","dns":2,"web":2,"email":2,"total":6,"rank":53},{"name":"karlskrona.se","dns":2,"web":-3,"email":2,"total":1,"rank":274},{"name":"karlstad.se","dns":2,"web":0,"email":2,"total":4,"rank":171},{"name":"katrineholm.se","dns":2,"web":4,"email":-1,"total":5,"rank":110},{"name":"kavlinge.se","dns":1,"web":2,"email":2,"total":5,"rank":113},{"name":"kil.se","dns":-2,"web":3,"email":0,"total":1,"rank":281},{"name":"kinda.se","dns":-1,"web":4,"email":2,"total":5,"rank":116},{"name":"kiruna.se","dns":1,"web":4,"email":-3,"total":2,"rank":228},{"name":"klippan.se","dns":2,"web":2,"email":0,"total":4,"rank":141},{"name":"knivsta.se","dns":1,"web":1,"email":2,"total":4,"rank":144},{"name":"koping.se","dns":1,"web":1,"email":-1,"total":1,"rank":272},{"name":"kramfors.se","dns":1,"web":4,"email":2,"total":7,"rank":36},{"name":"kristianstad.se","dns":2,"web":-1,"email":0,"total":1,"rank":276},{"name":"kristinehamn.se","dns":-1,"web":-1,"email":0,"total":-2,"rank":336},{"name":"krokom.se","dns":1,"web":1,"email":0,"total":2,"rank":235},{"name":"kumla.se","dns":-2,"web":1,"email":0,"total":-1,"rank":329},{"name":"kungalv.se","dns":1,"web":3,"email":2,"total":6,"rank":59},{"name":"kungsbacka.se","dns":1,"web":1,"email":3,"total":5,"rank":121},{"name":"kungsor.se","dns":1,"web":4,"email":2,"total":7,"rank":41},{"name":"laholm.se","dns":1,"web":1,"email":-1,"total":1,"rank":282},{"name":"landskrona.se","dns":2,"web":0,"email":3,"total":5,"rank":124},{"name":"laxa.se","dns":0,"web":4,"email":-2,"total":2,"rank":267},{"name":"lekeberg.se","dns":0,"web":4,"email":-4,"total":0,"rank":321},{"name":"leksand.se","dns":-1,"web":3,"email":0,"total":2,"rank":221},{"name":"lerum.se","dns":1,"web":1,"email":3,"total":5,"rank":125},{"name":"lessebo.se","dns":2,"web":4,"email":2,"total":8,"rank":8},{"name":"lidingo.se","dns":2,"web":2,"email":2,"total":6,"rank":64},{"name":"lidkoping.se","dns":1,"web":4,"email":1,"total":6,"rank":66},{"name":"lillaedet.se","dns":1,"web":4,"email":-1,"total":4,"rank":162},{"name":"lindesberg.se","dns":1,"web":4,"email":2,"total":7,"rank":44},{"name":"linkoping.se","dns":1,"web":1,"email":2,"total":4,"rank":165},{"name":"ljungby.se","dns":2,"web":-3,"email":0,"total":-1,"rank":330},{"name":"ljusdal.se","dns":2,"web":5,"email":1,"total":8,"rank":9},{"name":"ljusnarsberg.se","dns":1,"web":4,"email":0,"total":5,"rank":137},{"name":"lomma.se","dns":1,"web":1,"email":3,"total":5,"rank":93},{"name":"ludvika.se","dns":2,"web":4,"email":2,"total":8,"rank":10},{"name":"lulea.se","dns":2,"web":2,"email":2,"total":6,"rank":70},{"name":"lund.se","dns":2,"web":4,"email":3,"total":9,"rank":5},{"name":"lycksele.se","dns":-1,"web":1,"email":2,"total":2,"rank":260},{"name":"lysekil.se","dns":1,"web":4,"email":2,"total":7,"rank":24},{"name":"mala.se","dns":2,"web":3,"email":2,"total":7,"rank":25},{"name":"malmo.se","dns":1,"web":3,"email":2,"total":6,"rank":78},{"name":"malung-salen.se","dns":2,"web":4,"email":-1,"total":5,"rank":102},{"name":"mariestad.se","dns":1,"web":4,"email":0,"total":5,"rank":103},{"name":"markaryd.se","dns":2,"web":1,"email":2,"total":5,"rank":105},{"name":"mark.se","dns":2,"web":3,"email":1,"total":6,"rank":80},{"name":"mellerud.se","dns":2,"web":-1,"email":2,"total":3,"rank":202},{"name":"mjolby.se","dns":-2,"web":2,"email":-3,"total":-3,"rank":345},{"name":"molndal.se","dns":2,"web":4,"email":0,"total":6,"rank":81},{"name":"monsteras.se","dns":2,"web":1,"email":2,"total":5,"rank":109},{"name":"morakommun.se","dns":2,"web":4,"email":2,"total":8,"rank":12},{"name":"morbylanga.se","dns":-1,"web":-3,"email":-3,"total":-7,"rank":353},{"name":"motala.se","dns":2,"web":4,"email":0,"total":6,"rank":84},{"name":"mullsjo.se","dns":2,"web":2,"email":2,"total":6,"rank":87},{"name":"munkedal.se","dns":1,"web":4,"email":2,"total":7,"rank":27},{"name":"munkfors.se","dns":0,"web":3,"email":-3,"total":0,"rank":318},{"name":"nacka.se","dns":2,"web":-2,"email":2,"total":2,"rank":245},{"name":"nassjo.se","dns":2,"web":1,"email":3,"total":6,"rank":89},{"name":"nora.se","dns":2,"web":2,"email":-1,"total":3,"rank":216},{"name":"norberg.se","dns":2,"web":4,"email":0,"total":6,"rank":90},{"name":"nordanstig.se","dns":2,"web":4,"email":0,"total":6,"rank":91},{"name":"nordmaling.se","dns":1,"web":2,"email":-3,"total":0,"rank":322},{"name":"norrkoping.se","dns":1,"web":1,"email":-1,"total":1,"rank":285},{"name":"norrtalje.se","dns":1,"web":3,"email":2,"total":6,"rank":52},{"name":"norsjo.se","dns":2,"web":-4,"email":1,"total":-1,"rank":331},{"name":"nybro.se","dns":2,"web":3,"email":2,"total":7,"rank":28},{"name":"nykoping.se","dns":1,"web":1,"email":0,"total":2,"rank":224},{"name":"nykvarn.se","dns":2,"web":4,"email":0,"total":6,"rank":54},{"name":"nynashamn.se","dns":1,"web":1,"email":2,"total":4,"rank":173},{"name":"ockelbo.se","dns":2,"web":3,"email":0,"total":5,"rank":128},{"name":"ockero.se","dns":2,"web":2,"email":0,"total":4,"rank":187},{"name":"odeshog.se","dns":1,"web":4,"email":2,"total":7,"rank":29},{"name":"olofstrom.se","dns":2,"web":4,"email":0,"total":6,"rank":56},{"name":"orebro.se","dns":-2,"web":1,"email":2,"total":1,"rank":279},{"name":"orkelljunga.se","dns":2,"web":2,"email":0,"total":4,"rank":140},{"name":"ornskoldsvik.se","dns":1,"web":-1,"email":0,"total":0,"rank":309},{"name":"orsa.se","dns":2,"web":4,"email":0,"total":6,"rank":57},{"name":"orust.se","dns":1,"web":4,"email":0,"total":5,"rank":132},{"name":"osby.se","dns":1,"web":4,"email":0,"total":5,"rank":133},{"name":"oskarshamn.se","dns":2,"web":0,"email":0,"total":2,"rank":242},{"name":"osteraker.se","dns":2,"web":1,"email":-1,"total":2,"rank":244},{"name":"ostersund.se","dns":2,"web":2,"email":0,"total":4,"rank":148},{"name":"osthammar.se","dns":1,"web":0,"email":0,"total":1,"rank":269},{"name":"ostragoinge.se","dns":1,"web":1,"email":0,"total":2,"rank":249},{"name":"ovanaker.se","dns":2,"web":0,"email":1,"total":3,"rank":211},{"name":"overkalix.se","dns":2,"web":0,"email":0,"total":2,"rank":253},{"name":"overtornea.se","dns":2,"web":0,"email":0,"total":2,"rank":258},{"name":"oxelosund.se","dns":1,"web":4,"email":0,"total":5,"rank":134},{"name":"pajala.se","dns":2,"web":2,"email":2,"total":6,"rank":58},{"name":"partille.se","dns":2,"web":3,"email":2,"total":7,"rank":30},{"name":"perstorp.se","dns":2,"web":2,"email":0,"total":4,"rank":154},{"name":"pitea.se","dns":2,"web":1,"email":2,"total":5,"rank":92},{"name":"ragunda.se","dns":2,"web":5,"email":3,"total":10,"rank":1},{"name":"rattvik.se","dns":-1,"web":4,"email":2,"total":5,"rank":94},{"name":"robertsfors.se","dns":0,"web":0,"email":2,"total":2,"rank":226},{"name":"ronneby.se","dns":1,"web":4,"email":1,"total":6,"rank":61},{"name":"saffle.se","dns":2,"web":4,"email":0,"total":6,"rank":62},{"name":"sala.se","dns":2,"web":1,"email":0,"total":3,"rank":195},{"name":"salem.se","dns":2,"web":0,"email":2,"total":4,"rank":161},{"name":"sandviken.se","dns":2,"web":6,"email":1,"total":9,"rank":3},{"name":"sater.se","dns":2,"web":3,"email":2,"total":7,"rank":33},{"name":"savsjo.se","dns":2,"web":1,"email":3,"total":6,"rank":65},{"name":"sigtuna.se","dns":2,"web":4,"email":-3,"total":3,"rank":203},{"name":"simrishamn.se","dns":1,"web":1,"email":0,"total":2,"rank":238},{"name":"sjobo.se","dns":1,"web":2,"email":0,"total":3,"rank":204},{"name":"skara.se","dns":1,"web":2,"email":1,"total":4,"rank":166},{"name":"skelleftea.se","dns":1,"web":4,"email":3,"total":8,"rank":15},{"name":"skinnskatteberg.se","dns":0,"web":3,"email":2,"total":5,"rank":101},{"name":"skovde.se","dns":-2,"web":-2,"email":2,"total":-2,"rank":340},{"name":"skurup.se","dns":1,"web":-2,"email":2,"total":1,"rank":284},{"name":"smedjebacken.se","dns":2,"web":4,"email":2,"total":8,"rank":16},{"name":"soderhamn.se","dns":2,"web":4,"email":2,"total":8,"rank":17},{"name":"soderkoping.se","dns":1,"web":-1,"email":2,"total":2,"rank":251},{"name":"sodertalje.se","dns":2,"web":2,"email":0,"total":4,"rank":172},{"name":"solleftea.se","dns":2,"web":-2,"email":2,"total":2,"rank":257},{"name":"sollentuna.se","dns":2,"web":3,"email":0,"total":5,"rank":104},{"name":"solna.se","dns":1,"web":4,"email":-1,"total":4,"rank":175},{"name":"solvesborg.se","dns":-2,"web":4,"email":0,"total":2,"rank":262},{"name":"sorsele.se","dns":2,"web":0,"email":0,"total":2,"rank":266},{"name":"sotenas.se","dns":1,"web":1,"email":2,"total":4,"rank":185},{"name":"staffanstorp.se","dns":2,"web":-2,"email":2,"total":2,"rank":268},{"name":"stenungsund.se","dns":1,"web":4,"email":2,"total":7,"rank":37},{"name":"stockholm.se","dns":2,"web":3,"email":0,"total":5,"rank":106},{"name":"storfors.se","dns":-1,"web":4,"email":0,"total":3,"rank":220},{"name":"storuman.se","dns":2,"web":3,"email":2,"total":7,"rank":38},{"name":"strangnas.se","dns":2,"web":4,"email":0,"total":6,"rank":71},{"name":"stromstad.se","dns":1,"web":4,"email":2,"total":7,"rank":39},{"name":"stromsund.se","dns":2,"web":1,"email":0,"total":3,"rank":192},{"name":"sundbyberg.se","dns":1,"web":4,"email":2,"total":7,"rank":40},{"name":"sundsvall.se","dns":2,"web":0,"email":0,"total":2,"rank":229},{"name":"sunne.se","dns":2,"web":3,"email":-1,"total":4,"rank":142},{"name":"surahammar.se","dns":-2,"web":4,"email":2,"total":4,"rank":143},{"name":"svalov.se","dns":1,"web":4,"email":0,"total":5,"rank":111},{"name":"svedala.se","dns":2,"web":0,"email":0,"total":2,"rank":234},{"name":"svenljunga.se","dns":2,"web":2,"email":0,"total":4,"rank":145},{"name":"taby.se","dns":2,"web":0,"email":2,"total":4,"rank":146},{"name":"tanum.se","dns":1,"web":4,"email":0,"total":5,"rank":112},{"name":"tibro.se","dns":-2,"web":-2,"email":-1,"total":-5,"rank":352},{"name":"tidaholm.se","dns":1,"web":4,"email":1,"total":6,"rank":74},{"name":"tierp.se","dns":0,"web":2,"email":0,"total":2,"rank":240},{"name":"timra.se","dns":1,"web":2,"email":2,"total":5,"rank":114},{"name":"tingsryd.se","dns":2,"web":0,"email":2,"total":4,"rank":150},{"name":"tjorn.se","dns":1,"web":4,"email":0,"total":5,"rank":115},{"name":"tomelilla.se","dns":2,"web":4,"email":3,"total":9,"rank":4},{"name":"toreboda.se","dns":1,"web":4,"email":-2,"total":3,"rank":209},{"name":"torsas.se","dns":2,"web":1,"email":1,"total":4,"rank":153},{"name":"torsby.se","dns":2,"web":4,"email":0,"total":6,"rank":76},{"name":"tranas.se","dns":2,"web":1,"email":2,"total":5,"rank":118},{"name":"tranemo.se","dns":2,"web":3,"email":0,"total":5,"rank":119},{"name":"trelleborg.se","dns":1,"web":-1,"email":3,"total":3,"rank":215},{"name":"trollhattan.se","dns":2,"web":1,"email":1,"total":4,"rank":157},{"name":"trosa.se","dns":2,"web":0,"email":1,"total":3,"rank":217},{"name":"tyreso.se","dns":2,"web":4,"email":0,"total":6,"rank":77},{"name":"uddevalla.se","dns":1,"web":4,"email":2,"total":7,"rank":42},{"name":"ulricehamn.se","dns":2,"web":3,"email":0,"total":5,"rank":122},{"name":"umea.se","dns":1,"web":2,"email":3,"total":6,"rank":79},{"name":"upplands-bro.se","dns":2,"web":5,"email":3,"total":10,"rank":2},{"name":"upplandsvasby.se","dns":2,"web":1,"email":-3,"total":0,"rank":319},{"name":"uppsala.se","dns":1,"web":0,"email":2,"total":3,"rank":190},{"name":"uppvidinge.se","dns":2,"web":4,"email":2,"total":8,"rank":20},{"name":"vadstena.se","dns":0,"web":4,"email":0,"total":4,"rank":164},{"name":"vaggeryd.se","dns":2,"web":2,"email":-1,"total":3,"rank":193},{"name":"valdemarsvik.se","dns":1,"web":4,"email":0,"total":5,"rank":126},{"name":"vallentuna.se","dns":1,"web":-1,"email":0,"total":0,"rank":311},{"name":"vanersborg.se","dns":2,"web":2,"email":2,"total":6,"rank":82},{"name":"vannas.se","dns":2,"web":2,"email":-1,"total":3,"rank":196},{"name":"vansbro.se","dns":2,"web":1,"email":0,"total":3,"rank":197},{"name":"vara.se","dns":1,"web":0,"email":0,"total":1,"rank":271},{"name":"varberg.se","dns":1,"web":4,"email":2,"total":7,"rank":45},{"name":"vargarda.se","dns":0,"web":0,"email":2,"total":2,"rank":232},{"name":"varmdo.se","dns":1,"web":4,"email":2,"total":7,"rank":46},{"name":"varnamo.se","dns":2,"web":4,"email":0,"total":6,"rank":85},{"name":"vasteras.se","dns":2,"web":4,"email":-3,"total":3,"rank":201},{"name":"vastervik.se","dns":1,"web":3,"email":0,"total":4,"rank":170},{"name":"vaxholm.se","dns":2,"web":4,"email":0,"total":6,"rank":86},{"name":"vaxjo.se","dns":2,"web":4,"email":2,"total":8,"rank":21},{"name":"vellinge.se","dns":1,"web":2,"email":-1,"total":2,"rank":239},{"name":"vetlanda.se","dns":2,"web":2,"email":3,"total":7,"rank":48},{"name":"vilhelmina.se","dns":-1,"web":3,"email":2,"total":4,"rank":174},{"name":"vimmerby.se","dns":1,"web":4,"email":2,"total":7,"rank":49},{"name":"vindeln.se","dns":-2,"web":2,"email":2,"total":2,"rank":243},{"name":"vingaker.se","dns":2,"web":0,"email":-1,"total":1,"rank":290},{"name":"bromölla.se","dns":1,"web":0,"email":-2,"total":-1,"rank":324},{"name":"båstad.se","dns":1,"web":0,"email":0,"total":1,"rank":292},{"name":"öckerö.se","dns":1,"web":0,"email":0,"total":1,"rank":293},{"name":"ödeshög.se","dns":1,"web":-1,"email":0,"total":0,"rank":301},{"name":"eslöv.se","dns":1,"web":0,"email":0,"total":1,"rank":295},{"name":"finspång.se","dns":1,"web":0,"email":0,"total":1,"rank":296},{"name":"färgelanda.se","dns":1,"web":0,"email":-2,"total":-1,"rank":333},{"name":"gnosjö.se","dns":1,"web":0,"email":0,"total":1,"rank":297},{"name":"göteborg.se","dns":2,"web":0,"email":-1,"total":1,"rank":298},{"name":"götene.se","dns":-4,"web":0,"email":0,"total":-4,"rank":350},{"name":"gullspång.se","dns":1,"web":4,"email":-1,"total":4,"rank":176},{"name":"håbo.se","dns":1,"web":3,"email":0,"total":4,"rank":177},{"name":"höganäs.se","dns":2,"web":0,"email":0,"total":2,"rank":246},{"name":"höör.se","dns":1,"web":1,"email":0,"total":2,"rank":247},{"name":"härryda.se","dns":1,"web":0,"email":-1,"total":0,"rank":323},{"name":"hässleholm.se","dns":0,"web":0,"email":0,"total":0,"rank":300},{"name":"järfälla.se","dns":2,"web":0,"email":0,"total":2,"rank":248},{"name":"köping.se","dns":0,"web":0,"email":0,"total":0,"rank":302},{"name":"kungälv.se","dns":0,"web":0,"email":0,"total":0,"rank":303},{"name":"kungsör.se","dns":0,"web":0,"email":0,"total":0,"rank":305},{"name":"lidköping.se","dns":1,"web":0,"email":0,"total":1,"rank":273},{"name":"linköping.se","dns":-2,"web":-2,"email":0,"total":-4,"rank":349},{"name":"luleå.se","dns":1,"web":3,"email":0,"total":4,"rank":178},{"name":"älvkarleby.se","dns":1,"web":0,"email":0,"total":1,"rank":275},{"name":"mölndal.se","dns":2,"web":1,"email":1,"total":4,"rank":179},{"name":"mönsterås.se","dns":0,"web":0,"email":0,"total":0,"rank":313},{"name":"mörbylånga.se","dns":1,"web":0,"email":-1,"total":0,"rank":314},{"name":"mullsjö.se","dns":-2,"web":0,"email":-2,"total":-4,"rank":351},{"name":"ånge.se","dns":1,"web":0,"email":-1,"total":0,"rank":315},{"name":"norrköping.se","dns":1,"web":0,"email":-1,"total":0,"rank":316},{"name":"norrtälje.se","dns":-4,"web":0,"email":0,"total":-4,"rank":348},{"name":"norsjö.se","dns":2,"web":0,"email":2,"total":4,"rank":180},{"name":"nässjö.se","dns":2,"web":0,"email":0,"total":2,"rank":252},{"name":"nyköping.se","dns":1,"web":3,"email":0,"total":4,"rank":181},{"name":"olofström.se","dns":1,"web":0,"email":1,"total":2,"rank":254},{"name":"ovanåker.se","dns":2,"web":0,"email":0,"total":2,"rank":255},{"name":"åre.se","dns":2,"web":0,"email":0,"total":2,"rank":256},{"name":"rättvik.se","dns":1,"web":0,"email":0,"total":1,"rank":283},{"name":"söderhamn.se","dns":2,"web":1,"email":0,"total":3,"rank":214},{"name":"söderköping.se","dns":2,"web":0,"email":2,"total":4,"rank":182},{"name":"södertälje.se","dns":1,"web":0,"email":-1,"total":0,"rank":304},{"name":"säffle.se","dns":1,"web":0,"email":-2,"total":-1,"rank":325},{"name":"sjöbo.se","dns":1,"web":0,"email":0,"total":1,"rank":286},{"name":"skövde.se","dns":-2,"web":0,"email":0,"total":-2,"rank":339},{"name":"sölvesborg.se","dns":1,"web":0,"email":-2,"total":-1,"rank":327},{"name":"sollefteå.se","dns":1,"web":0,"email":0,"total":1,"rank":287},{"name":"österåker.se","dns":1,"web":0,"email":-1,"total":0,"rank":307},{"name":"säter.se","dns":2,"web":0,"email":0,"total":2,"rank":259},{"name":"åstorp.se","dns":1,"web":3,"email":0,"total":4,"rank":183},{"name":"strängnäs.se","dns":1,"web":0,"email":-1,"total":0,"rank":310},{"name":"svalöv.se","dns":1,"web":1,"email":0,"total":2,"rank":261},{"name":"åtvidaberg.se","dns":1,"web":0,"email":-1,"total":0,"rank":312},{"name":"tyresö.se","dns":1,"web":0,"email":0,"total":1,"rank":291},{"name":"umeå.se","dns":1,"web":1,"email":2,"total":4,"rank":184},{"name":"upplandsväsby.se","dns":1,"web":1,"email":0,"total":2,"rank":263},{"name":"vingåker.se","dns":1,"web":0,"email":0,"total":1,"rank":294},{"name":"vänersborg.se","dns":-1,"web":0,"email":0,"total":-1,"rank":328},{"name":"värmdö.se","dns":0,"web":0,"email":0,"total":0,"rank":317},{"name":"värnamo.se","dns":2,"web":0,"email":0,"total":2,"rank":264},{"name":"västerås.se","dns":2,"web":0,"email":0,"total":2,"rank":265},{"name":"västervik.se","dns":0,"web":0,"email":0,"total":0,"rank":320},{"name":"växjö.se","dns":2,"web":3,"email":0,"total":5,"rank":135},{"name":"ydre.se","dns":1,"web":4,"email":2,"total":7,"rank":50},{"name":"ystad.se","dns":1,"web":3,"email":3,"total":7,"rank":51}],"rank":7},{"name":"Media","id":"media","dns":18,"web":32,"email":2,"total":52,"hosts":[{"name":"cmore.se","dns":1,"web":5,"email":-1,"total":5,"rank":4},{"name":"dplay.se","dns":1,"web":3,"email":-1,"total":3,"rank":11},{"name":"ilikeradio.se","dns":1,"web":4,"email":2,"total":7,"rank":1},{"name":"kanal5.se","dns":1,"web":0,"email":3,"total":4,"rank":8},{"name":"mixmegapol.se","dns":1,"web":0,"email":2,"total":3,"rank":9},{"name":"nrj.se","dns":1,"web":0,"email":2,"total":3,"rank":10},{"name":"radioplay.se","dns":1,"web":2,"email":2,"total":5,"rank":7},{"name":"rixfm.se","dns":1,"web":0,"email":2,"total":3,"rank":13},{"name":"sverigesradio.se","dns":1,"web":2,"email":3,"total":6,"rank":2},{"name":"svtplay.se","dns":1,"web":2,"email":2,"total":5,"rank":5},{"name":"svt.se","dns":1,"web":2,"email":2,"total":5,"rank":6},{"name":"tv3.se","dns":1,"web":0,"email":-3,"total":-2,"rank":17},{"name":"tv4play.se","dns":1,"web":1,"email":-3,"total":-1,"rank":15},{"name":"tv4.se","dns":1,"web":3,"email":-3,"total":1,"rank":14},{"name":"tv6.se","dns":1,"web":5,"email":-3,"total":3,"rank":12},{"name":"tv8.se","dns":1,"web":0,"email":-3,"total":-2,"rank":16},{"name":"viafree.se","dns":1,"web":3,"email":2,"total":6,"rank":3},{"name":"viasat.se","dns":1,"web":0,"email":-3,"total":-2,"rank":18}],"rank":11},{"name":"Regioner","id":"regioner","dns":23,"web":23,"email":27,"total":73,"hosts":[{"name":"gotland.se","dns":2,"web":1,"email":2,"total":5,"rank":8},{"name":"norrbotten.se","dns":2,"web":-3,"email":0,"total":-1,"rank":21},{"name":"regionblekinge.se","dns":2,"web":1,"email":0,"total":3,"rank":13},{"name":"regiondalarna.se","dns":2,"web":3,"email":0,"total":5,"rank":6},{"name":"regiongavleborg.se","dns":2,"web":3,"email":2,"total":7,"rank":3},{"name":"regionhalland.se","dns":1,"web":-1,"email":2,"total":2,"rank":14},{"name":"regionjh.se","dns":2,"web":4,"email":3,"total":9,"rank":1},{"name":"regionkalmar.se","dns":2,"web":4,"email":2,"total":8,"rank":2},{"name":"regionkronoberg.se","dns":2,"web":-3,"email":1,"total":0,"rank":19},{"name":"regionorebrolan.se","dns":2,"web":3,"email":2,"total":7,"rank":4},{"name":"regionostergotland.se","dns":2,"web":1,"email":1,"total":4,"rank":9},{"name":"regionsormland.se","dns":0,"web":0,"email":0,"total":0,"rank":16},{"name":"regionuppsala.se","dns":1,"web":0,"email":2,"total":3,"rank":11},{"name":"regionvarmland.se","dns":-2,"web":2,"email":2,"total":2,"rank":15},{"name":"regionvasterbotten.se","dns":-1,"web":-2,"email":3,"total":0,"rank":18},{"name":"regionvastmanland.se","dns":2,"web":1,"email":2,"total":5,"rank":7},{"name":"rjl.se","dns":2,"web":5,"email":0,"total":7,"rank":5},{"name":"rvn.se","dns":1,"web":-1,"email":0,"total":0,"rank":17},{"name":"skane.se","dns":-1,"web":2,"email":2,"total":3,"rank":12},{"name":"sll.se","dns":1,"web":3,"email":0,"total":4,"rank":10},{"name":"vgregion.se","dns":-1,"web":0,"email":1,"total":0,"rank":20}],"rank":5},{"name":"Registrarer","id":"registrarer","dns":129,"web":174,"email":112,"total":415,"hosts":[{"name":"100procent.com","dns":1,"web":1,"email":2,"total":4,"rank":55},{"name":"101domain.com","dns":2,"web":2,"email":0,"total":4,"rank":45},{"name":"1198.cn","dns":1,"web":0,"email":0,"total":1,"rank":103},{"name":"123domain.eu","dns":1,"web":1,"email":-1,"total":1,"rank":106},{"name":"1and1.com","dns":1,"web":3,"email":0,"total":4,"rank":48},{"name":"1api.net","dns":1,"web":2,"email":2,"total":5,"rank":32},{"name":"28kdigital.com","dns":-1,"web":0,"email":1,"total":0,"rank":120},{"name":"ascio.com","dns":1,"web":3,"email":0,"total":4,"rank":43},{"name":"atellus.se","dns":-2,"web":0,"email":-4,"total":-6,"rank":132},{"name":"ballou.se","dns":1,"web":0,"email":1,"total":2,"rank":92},{"name":"beebyte.se","dns":1,"web":3,"email":2,"total":6,"rank":20},{"name":"bgpm.se","dns":1,"web":0,"email":1,"total":2,"rank":85},{"name":"bluesnap.io","dns":1,"web":3,"email":1,"total":5,"rank":39},{"name":"buildit.net","dns":1,"web":3,"email":1,"total":5,"rank":28},{"name":"buildit.se","dns":1,"web":2,"email":1,"total":4,"rank":42},{"name":"comlaude.com","dns":2,"web":4,"email":2,"total":8,"rank":7},{"name":"corehub.net","dns":1,"web":3,"email":2,"total":6,"rank":23},{"name":"cps-datensysteme.de","dns":1,"web":1,"email":1,"total":3,"rank":68},{"name":"crossnet.net","dns":1,"web":0,"email":0,"total":1,"rank":100},{"name":"crossnet.se","dns":1,"web":1,"email":-1,"total":1,"rank":101},{"name":"crystone.se","dns":2,"web":3,"email":1,"total":6,"rank":25},{"name":"cscglobal.com","dns":2,"web":3,"email":-3,"total":2,"rank":80},{"name":"dn.ee","dns":1,"web":0,"email":2,"total":3,"rank":75},{"name":"dnr.emea.verizonbusiness.com","dns":1,"web":1,"email":0,"total":2,"rank":86},{"name":"domaindiscount24.com","dns":1,"web":2,"email":2,"total":5,"rank":31},{"name":"domains.rackfish.com","dns":1,"web":1,"email":0,"total":2,"rank":97},{"name":"domanregister.se","dns":1,"web":0,"email":3,"total":4,"rank":60},{"name":"domanservice.se","dns":-2,"web":3,"email":1,"total":2,"rank":81},{"name":"domanshop.se","dns":2,"web":3,"email":4,"total":9,"rank":3},{"name":"dotkeeper.com","dns":1,"web":1,"email":3,"total":5,"rank":34},{"name":"drs.knipp.de","dns":1,"web":1,"email":0,"total":2,"rank":90},{"name":"edomains.com","dns":1,"web":3,"email":2,"total":6,"rank":21},{"name":"edoms.com","dns":2,"web":0,"email":0,"total":2,"rank":96},{"name":"egensajt.se","dns":2,"web":1,"email":2,"total":5,"rank":27},{"name":"ember.se","dns":1,"web":1,"email":-1,"total":1,"rank":109},{"name":"enom.com","dns":1,"web":3,"email":0,"total":4,"rank":49},{"name":"epag.de","dns":1,"web":3,"email":0,"total":4,"rank":54},{"name":"eurodns.com","dns":1,"web":-1,"email":0,"total":0,"rank":121},{"name":"excedodms.se","dns":2,"web":0,"email":0,"total":2,"rank":82},{"name":"forss.se","dns":1,"web":1,"email":-1,"total":1,"rank":104},{"name":"frobbit.se","dns":2,"web":5,"email":4,"total":11,"rank":1},{"name":"fsdata.se","dns":1,"web":-2,"email":2,"total":1,"rank":107},{"name":"ftech.se","dns":1,"web":3,"email":3,"total":7,"rank":11},{"name":"gandi.net","dns":1,"web":0,"email":0,"total":1,"rank":110},{"name":"gotanet.se","dns":2,"web":-2,"email":1,"total":1,"rank":112},{"name":"gratisdns.com","dns":1,"web":0,"email":0,"total":1,"rank":113},{"name":"griffel.se","dns":1,"web":-4,"email":2,"total":-1,"rank":126},{"name":"groth.se","dns":1,"web":3,"email":0,"total":4,"rank":61},{"name":"hertigtorulf.se","dns":2,"web":3,"email":-1,"total":4,"rank":62},{"name":"hostnet.nl","dns":-2,"web":-3,"email":-3,"total":-8,"rank":133},{"name":"ilait.com","dns":1,"web":3,"email":0,"total":4,"rank":41},{"name":"inbrand.se","dns":2,"web":1,"email":3,"total":6,"rank":17},{"name":"indukon.se","dns":0,"web":3,"email":3,"total":6,"rank":18},{"name":"infracom.se","dns":1,"web":3,"email":2,"total":6,"rank":19},{"name":"inleed.se","dns":1,"web":3,"email":3,"total":7,"rank":10},{"name":"instra.com","dns":1,"web":0,"email":1,"total":2,"rank":83},{"name":"internetsrs.com","dns":-2,"web":0,"email":1,"total":-1,"rank":124},{"name":"internetstiftelsen.se","dns":2,"web":2,"email":4,"total":8,"rank":4},{"name":"internetvikings.com","dns":1,"web":1,"email":2,"total":4,"rank":52},{"name":"internetx.com","dns":1,"web":-1,"email":0,"total":0,"rank":118},{"name":"intripid.com","dns":1,"web":1,"email":3,"total":5,"rank":30},{"name":"inwx.com","dns":2,"web":2,"email":3,"total":7,"rank":15},{"name":"itconnect.se","dns":-1,"web":1,"email":0,"total":0,"rank":116},{"name":"itkoncept.se","dns":1,"web":0,"email":2,"total":3,"rank":70},{"name":"joker.com","dns":1,"web":1,"email":2,"total":4,"rank":56},{"name":"koneo.se","dns":-1,"web":0,"email":3,"total":2,"rank":79},{"name":"kontorsspecial.se","dns":1,"web":0,"email":2,"total":3,"rank":78},{"name":"levonline.com","dns":1,"web":3,"email":0,"total":4,"rank":57},{"name":"lexsynergy.com","dns":2,"web":3,"email":1,"total":6,"rank":24},{"name":"loopia.se","dns":0,"web":3,"email":4,"total":7,"rank":8},{"name":"lopnet.se","dns":-2,"web":0,"email":-3,"total":-5,"rank":131},{"name":"markmonitor.com","dns":1,"web":0,"email":1,"total":2,"rank":84},{"name":"metaregistrar.com","dns":2,"web":0,"email":3,"total":5,"rank":38},{"name":"mono.net","dns":1,"web":0,"email":-1,"total":0,"rank":119},{"name":"mrdomain.com","dns":1,"web":1,"email":1,"total":3,"rank":67},{"name":"name.com","dns":-1,"web":1,"email":2,"total":2,"rank":89},{"name":"nameisp.com","dns":2,"web":3,"email":-1,"total":4,"rank":63},{"name":"namesrs.com","dns":1,"web":-2,"email":-2,"total":-3,"rank":128},{"name":"nameweb.biz","dns":1,"web":0,"email":0,"total":1,"rank":105},{"name":"netim.com","dns":1,"web":-1,"email":-1,"total":-1,"rank":125},{"name":"neware.se","dns":1,"web":0,"email":1,"total":2,"rank":91},{"name":"nicsell.com","dns":1,"web":0,"email":3,"total":4,"rank":66},{"name":"nmugroup.com","dns":2,"web":1,"email":4,"total":7,"rank":9},{"name":"nominate.com","dns":2,"web":3,"email":-2,"total":3,"rank":76},{"name":"nordichosting.com","dns":1,"web":1,"email":1,"total":3,"rank":77},{"name":"nunames.nu","dns":1,"web":4,"email":0,"total":5,"rank":26},{"name":"oderland.se","dns":1,"web":4,"email":3,"total":8,"rank":5},{"name":"odibo.se","dns":1,"web":4,"email":-1,"total":4,"rank":44},{"name":"one.com","dns":2,"web":2,"email":4,"total":8,"rank":6},{"name":"openprovider.com","dns":2,"web":-1,"email":-1,"total":0,"rank":117},{"name":"ovh.com","dns":1,"web":1,"email":2,"total":4,"rank":46},{"name":"pixel.se","dns":0,"web":3,"email":1,"total":4,"rank":47},{"name":"portsgroup.com","dns":2,"web":0,"email":3,"total":5,"rank":29},{"name":"proisp.no","dns":1,"web":5,"email":1,"total":7,"rank":12},{"name":"quicknet.se","dns":1,"web":0,"email":0,"total":1,"rank":108},{"name":"readydigital.se","dns":1,"web":1,"email":2,"total":4,"rank":50},{"name":"realtimeregister.com","dns":1,"web":0,"email":3,"total":4,"rank":51},{"name":"redsnapper.nu","dns":1,"web":3,"email":-1,"total":3,"rank":69},{"name":"register.eu","dns":1,"web":1,"email":0,"total":2,"rank":94},{"name":"registrar.nl","dns":0,"web":0,"email":2,"total":2,"rank":95},{"name":"registrar-proxy.nl","dns":0,"web":0,"email":0,"total":0,"rank":122},{"name":"registrera-doman.se","dns":2,"web":3,"email":2,"total":7,"rank":13},{"name":"regit.nu","dns":1,"web":0,"email":-2,"total":-1,"rank":123},{"name":"rymdweb.se","dns":2,"web":1,"email":0,"total":3,"rank":71},{"name":"safebrands.fr","dns":2,"web":1,"email":-1,"total":2,"rank":98},{"name":"safenames.net","dns":1,"web":2,"email":0,"total":3,"rank":74},{"name":"sarek.fi","dns":2,"web":3,"email":-1,"total":4,"rank":53},{"name":"scandinavianhosting.se","dns":1,"web":3,"email":2,"total":6,"rank":22},{"name":"secure.nameshield.net","dns":1,"web":2,"email":2,"total":5,"rank":33},{"name":"servercentralen.se","dns":1,"web":3,"email":3,"total":7,"rank":14},{"name":"simply.com","dns":2,"web":2,"email":1,"total":5,"rank":35},{"name":"sircon.no","dns":1,"web":3,"email":0,"total":4,"rank":58},{"name":"space2u.com","dns":1,"web":3,"email":0,"total":4,"rank":59},{"name":"spacedump.se","dns":2,"web":1,"email":-2,"total":1,"rank":115},{"name":"standardbolaginternet.se","dns":1,"web":1,"email":0,"total":2,"rank":87},{"name":"sveabyran.se","dns":1,"web":1,"email":0,"total":2,"rank":88},{"name":"svenskadomaner.se","dns":1,"web":-2,"email":2,"total":1,"rank":102},{"name":"svenskaexportmedia.com","dns":-2,"web":0,"email":-1,"total":-3,"rank":127},{"name":"telia.se","dns":1,"web":2,"email":2,"total":5,"rank":36},{"name":"theregistrarcompany.com","dns":2,"web":3,"email":0,"total":5,"rank":37},{"name":"united-domains.de","dns":1,"web":2,"email":0,"total":3,"rank":72},{"name":"variomedia.de","dns":1,"web":-2,"email":-3,"total":-4,"rank":129},{"name":"vmi.se","dns":1,"web":0,"email":2,"total":3,"rank":73},{"name":"wannafind.dk","dns":1,"web":1,"email":0,"total":2,"rank":93},{"name":"webb.se","dns":2,"web":5,"email":3,"total":10,"rank":2},{"name":"webhotellet.net","dns":1,"web":4,"email":2,"total":7,"rank":16},{"name":"weblovers.com","dns":1,"web":1,"email":2,"total":4,"rank":64},{"name":"web-solutions.eu","dns":1,"web":0,"email":0,"total":1,"rank":111},{"name":"wiredequity.com","dns":1,"web":2,"email":1,"total":4,"rank":65},{"name":"wk.se","dns":1,"web":2,"email":2,"total":5,"rank":40},{"name":"wopsa.se","dns":1,"web":1,"email":-1,"total":1,"rank":114},{"name":"yamito.se","dns":1,"web":1,"email":0,"total":2,"rank":99},{"name":"yask.se","dns":-2,"web":-2,"email":0,"total":-4,"rank":130}],"rank":8},{"name":"Statliga myndigheter","id":"statligamyndigheter","dns":216,"web":226,"email":136,"total":578,"hosts":[{"name":"aklagare.se","dns":2,"web":5,"email":2,"total":9,"rank":3},{"name":"arbetsdomstolen.se","dns":1,"web":-2,"email":-1,"total":-2,"rank":190},{"name":"arbetsformedlingen.se","dns":2,"web":1,"email":3,"total":6,"rank":27},{"name":"arbetsgivarverket.se","dns":1,"web":0,"email":2,"total":3,"rank":107},{"name":"arkdes.se","dns":0,"web":3,"email":1,"total":4,"rank":65},{"name":"arn.se","dns":1,"web":1,"email":0,"total":2,"rank":120},{"name":"av.se","dns":1,"web":3,"email":0,"total":4,"rank":77},{"name":"barnombudsmannen.se","dns":2,"web":0,"email":-1,"total":1,"rank":129},{"name":"bfn.se","dns":2,"web":3,"email":-1,"total":4,"rank":57},{"name":"bolagsverket.se","dns":1,"web":1,"email":-1,"total":1,"rank":134},{"name":"bo.se","dns":2,"web":0,"email":-1,"total":1,"rank":136},{"name":"boverket.se","dns":2,"web":-1,"email":-3,"total":-2,"rank":187},{"name":"bra.se","dns":2,"web":-2,"email":1,"total":1,"rank":138},{"name":"brottsoffermyndigheten.se","dns":1,"web":1,"email":-4,"total":-2,"rank":186},{"name":"cert.se","dns":2,"web":1,"email":4,"total":7,"rank":18},{"name":"csn.se","dns":2,"web":4,"email":3,"total":9,"rank":2},{"name":"delmos.se","dns":-2,"web":3,"email":2,"total":3,"rank":102},{"name":"digg.se","dns":2,"web":2,"email":1,"total":5,"rank":39},{"name":"dom.se","dns":2,"web":0,"email":0,"total":2,"rank":116},{"name":"domstol.se","dns":2,"web":0,"email":1,"total":3,"rank":96},{"name":"do.se","dns":1,"web":-1,"email":3,"total":3,"rank":97},{"name":"ehalsomyndigheten.se","dns":2,"web":0,"email":3,"total":5,"rank":54},{"name":"ei.se","dns":2,"web":4,"email":2,"total":8,"rank":9},{"name":"ekn.se","dns":2,"web":1,"email":0,"total":3,"rank":110},{"name":"ekobrottsmyndigheten.se","dns":2,"web":1,"email":2,"total":5,"rank":42},{"name":"elsakerhetsverket.se","dns":1,"web":3,"email":0,"total":4,"rank":64},{"name":"energimyndigheten.se","dns":2,"web":1,"email":2,"total":5,"rank":47},{"name":"epn.se","dns":1,"web":0,"email":-1,"total":0,"rank":164},{"name":"esf.se","dns":1,"web":0,"email":0,"total":1,"rank":133},{"name":"esv.se","dns":0,"web":2,"email":1,"total":3,"rank":103},{"name":"etikprovningsmyndigheten.se","dns":1,"web":2,"email":-1,"total":2,"rank":121},{"name":"fba.se","dns":2,"web":3,"email":0,"total":5,"rank":51},{"name":"finanspolitiskaradet.se","dns":1,"web":0,"email":0,"total":1,"rank":151},{"name":"fi.se","dns":2,"web":5,"email":-1,"total":6,"rank":33},{"name":"fmi.se","dns":0,"web":1,"email":2,"total":3,"rank":83},{"name":"fmv.se","dns":2,"web":1,"email":0,"total":3,"rank":84},{"name":"foi.se","dns":1,"web":1,"email":2,"total":4,"rank":63},{"name":"folkhalsomyndigheten.se","dns":-2,"web":1,"email":0,"total":-1,"rank":178},{"name":"formas.se","dns":2,"web":4,"email":0,"total":6,"rank":37},{"name":"forsakringskassan.se","dns":2,"web":-2,"email":2,"total":2,"rank":112},{"name":"forsvarsmakten.se","dns":2,"web":2,"email":2,"total":6,"rank":26},{"name":"forte.se","dns":1,"web":0,"email":0,"total":1,"rank":131},{"name":"fortifikationsverket.se","dns":2,"web":2,"email":3,"total":7,"rank":16},{"name":"fortv.se","dns":2,"web":3,"email":3,"total":8,"rank":8},{"name":"fra.se","dns":2,"web":3,"email":1,"total":6,"rank":35},{"name":"havkom.se","dns":2,"web":0,"email":0,"total":2,"rank":113},{"name":"havochvatten.se","dns":2,"web":-1,"email":0,"total":1,"rank":140},{"name":"iaf.se","dns":0,"web":-1,"email":0,"total":-1,"rank":175},{"name":"ifau.se","dns":0,"web":-1,"email":2,"total":1,"rank":146},{"name":"imy.se","dns":2,"web":0,"email":0,"total":2,"rank":114},{"name":"irf.se","dns":-1,"web":-3,"email":3,"total":-1,"rank":177},{"name":"isf.se","dns":0,"web":4,"email":1,"total":5,"rank":38},{"name":"isof.se","dns":1,"web":4,"email":2,"total":7,"rank":13},{"name":"isp.se","dns":0,"web":3,"email":0,"total":3,"rank":88},{"name":"ivo.se","dns":2,"web":1,"email":0,"total":3,"rank":90},{"name":"jamstalldhetsmyndigheten.se","dns":0,"web":2,"email":2,"total":4,"rank":67},{"name":"jk.se","dns":1,"web":-2,"email":0,"total":-1,"rank":176},{"name":"jordbruksverket.se","dns":2,"web":2,"email":0,"total":4,"rank":71},{"name":"jo.se","dns":1,"web":0,"email":1,"total":2,"rank":115},{"name":"justitiekanslern.se","dns":1,"web":-2,"email":0,"total":-1,"rank":183},{"name":"kammarkollegiet.se","dns":1,"web":2,"email":0,"total":3,"rank":100},{"name":"karnavfallsfonden.se","dns":1,"web":1,"email":-1,"total":1,"rank":148},{"name":"kb.se","dns":2,"web":-2,"email":0,"total":0,"rank":159},{"name":"kemi.se","dns":0,"web":2,"email":2,"total":4,"rank":72},{"name":"ki.se","dns":0,"web":-2,"email":2,"total":0,"rank":158},{"name":"kkv.se","dns":1,"web":0,"email":0,"total":1,"rank":127},{"name":"kommerskollegium.se","dns":1,"web":3,"email":0,"total":4,"rank":74},{"name":"konj.se","dns":2,"web":4,"email":0,"total":6,"rank":22},{"name":"konkurrensverket.se","dns":1,"web":2,"email":0,"total":3,"rank":108},{"name":"konstfack.se","dns":2,"web":2,"email":0,"total":4,"rank":56},{"name":"konstnarsnamnden.se","dns":2,"web":1,"email":2,"total":5,"rank":45},{"name":"konsumentverket.se","dns":2,"web":3,"email":-1,"total":4,"rank":61},{"name":"kriminalvarden.se","dns":1,"web":1,"email":0,"total":2,"rank":117},{"name":"kronofogden.se","dns":2,"web":0,"email":4,"total":6,"rank":23},{"name":"kulturanalys.se","dns":0,"web":3,"email":2,"total":5,"rank":50},{"name":"kulturradet.se","dns":2,"web":-2,"email":2,"total":2,"rank":126},{"name":"kungahuset.se","dns":0,"web":4,"email":2,"total":6,"rank":25},{"name":"kustbevakningen.se","dns":2,"web":3,"email":0,"total":5,"rank":53},{"name":"lakemedelsverket.se","dns":1,"web":2,"email":0,"total":3,"rank":98},{"name":"lansstyrelsen.se","dns":2,"web":4,"email":4,"total":10,"rank":1},{"name":"lantmateriet.se","dns":2,"web":5,"email":0,"total":7,"rank":17},{"name":"levandehistoria.se","dns":2,"web":2,"email":2,"total":6,"rank":32},{"name":"lfv.se","dns":2,"web":1,"email":-3,"total":0,"rank":170},{"name":"livsmedelsverket.se","dns":2,"web":1,"email":0,"total":3,"rank":104},{"name":"lm.se","dns":1,"web":3,"email":-1,"total":3,"rank":106},{"name":"mfd.se","dns":-1,"web":1,"email":0,"total":0,"rank":160},{"name":"mfof.se","dns":2,"web":4,"email":-1,"total":5,"rank":40},{"name":"migrationsverket.se","dns":2,"web":4,"email":2,"total":8,"rank":6},{"name":"mil.se","dns":2,"web":0,"email":1,"total":3,"rank":109},{"name":"mi.se","dns":1,"web":0,"email":-2,"total":-1,"rank":180},{"name":"modernamuseet.se","dns":0,"web":-1,"email":0,"total":-1,"rank":181},{"name":"mpa.se","dns":1,"web":3,"email":-3,"total":1,"rank":152},{"name":"mprt.se","dns":1,"web":2,"email":2,"total":5,"rank":43},{"name":"msb.se","dns":2,"web":1,"email":0,"total":3,"rank":111},{"name":"mtm.se","dns":1,"web":1,"email":2,"total":4,"rank":59},{"name":"mucf.se","dns":0,"web":0,"email":0,"total":0,"rank":171},{"name":"musikverket.se","dns":1,"web":3,"email":3,"total":7,"rank":19},{"name":"myh.se","dns":0,"web":1,"email":2,"total":3,"rank":85},{"name":"mynak.se","dns":0,"web":1,"email":2,"total":3,"rank":87},{"name":"myndighetensst.se","dns":-2,"web":1,"email":0,"total":-1,"rank":174},{"name":"nai.uu.se","dns":1,"web":-1,"email":2,"total":2,"rank":122},{"name":"nationalmuseum.se","dns":1,"web":3,"email":0,"total":4,"rank":62},{"name":"naturvardsverket.se","dns":2,"web":-2,"email":3,"total":3,"rank":89},{"name":"nrm.se","dns":-2,"web":2,"email":0,"total":0,"rank":156},{"name":"oks.se","dns":-2,"web":-1,"email":2,"total":-1,"rank":179},{"name":"onep.se","dns":2,"web":3,"email":0,"total":5,"rank":46},{"name":"oredlighetsprovning.se","dns":1,"web":-2,"email":2,"total":1,"rank":150},{"name":"pensionsmyndigheten.se","dns":2,"web":1,"email":0,"total":3,"rank":92},{"name":"pliktverket.se","dns":1,"web":2,"email":0,"total":3,"rank":95},{"name":"polar.se","dns":2,"web":3,"email":2,"total":7,"rank":12},{"name":"polisen.se","dns":2,"web":2,"email":4,"total":8,"rank":7},{"name":"prv.se","dns":-1,"web":0,"email":3,"total":2,"rank":119},{"name":"pts.se","dns":2,"web":1,"email":4,"total":7,"rank":14},{"name":"raa.se","dns":2,"web":4,"email":0,"total":6,"rank":24},{"name":"regeringen.se","dns":2,"web":1,"email":0,"total":3,"rank":101},{"name":"regeringskansliet.se","dns":2,"web":-2,"email":0,"total":0,"rank":163},{"name":"revisorsinspektionen.se","dns":1,"web":1,"email":0,"total":2,"rank":123},{"name":"riksarkivet.se","dns":2,"web":-2,"email":0,"total":0,"rank":169},{"name":"riksdagen.se","dns":2,"web":2,"email":3,"total":7,"rank":15},{"name":"riksgalden.se","dns":-1,"web":0,"email":2,"total":1,"rank":141},{"name":"riksrevisionen.se","dns":2,"web":4,"email":3,"total":9,"rank":4},{"name":"rmv.se","dns":1,"web":0,"email":0,"total":1,"rank":147},{"name":"rymdstyrelsen.se","dns":2,"web":3,"email":-1,"total":4,"rank":75},{"name":"sakerhetspolisen.se","dns":1,"web":5,"email":3,"total":9,"rank":5},{"name":"sakint.se","dns":2,"web":2,"email":0,"total":4,"rank":78},{"name":"sameskolstyrelsen.se","dns":0,"web":3,"email":1,"total":4,"rank":81},{"name":"sametinget.se","dns":1,"web":-1,"email":0,"total":0,"rank":167},{"name":"sbu.se","dns":0,"web":3,"email":-3,"total":0,"rank":168},{"name":"scb.se","dns":2,"web":1,"email":3,"total":6,"rank":28},{"name":"sfhm.se","dns":1,"web":0,"email":0,"total":1,"rank":128},{"name":"sfv.se","dns":0,"web":2,"email":3,"total":5,"rank":41},{"name":"sgi.se","dns":1,"web":3,"email":0,"total":4,"rank":58},{"name":"sgu.se","dns":1,"web":0,"email":0,"total":1,"rank":132},{"name":"shm.se","dns":1,"web":3,"email":-1,"total":3,"rank":82},{"name":"sida.se","dns":2,"web":3,"email":1,"total":6,"rank":29},{"name":"sieps.se","dns":0,"web":2,"email":2,"total":4,"rank":60},{"name":"si.se","dns":1,"web":3,"email":2,"total":6,"rank":30},{"name":"siun.se","dns":1,"web":-2,"email":2,"total":1,"rank":139},{"name":"sjofartsverket.se","dns":2,"web":1,"email":0,"total":3,"rank":86},{"name":"skatteverket.se","dns":2,"web":-1,"email":4,"total":5,"rank":44},{"name":"skogsstyrelsen.se","dns":1,"web":-1,"email":1,"total":1,"rank":143},{"name":"skolfi.se","dns":1,"web":3,"email":2,"total":6,"rank":31},{"name":"skolinspektionen.se","dns":1,"web":4,"email":3,"total":8,"rank":10},{"name":"skolverket.se","dns":2,"web":4,"email":2,"total":8,"rank":11},{"name":"slv.se","dns":1,"web":0,"email":0,"total":1,"rank":149},{"name":"smhi.se","dns":2,"web":-1,"email":2,"total":3,"rank":91},{"name":"smtm.se","dns":1,"web":-1,"email":0,"total":0,"rank":162},{"name":"snsb.se","dns":2,"web":0,"email":0,"total":2,"rank":118},{"name":"socialstyrelsen.se","dns":2,"web":2,"email":0,"total":4,"rank":66},{"name":"spelinspektionen.se","dns":1,"web":0,"email":0,"total":1,"rank":153},{"name":"sprakochfolkminnen.se","dns":1,"web":0,"email":2,"total":3,"rank":93},{"name":"spsm.se","dns":2,"web":1,"email":0,"total":3,"rank":94},{"name":"spv.se","dns":2,"web":1,"email":2,"total":5,"rank":48},{"name":"ssm.se","dns":1,"web":1,"email":-3,"total":-1,"rank":173},{"name":"statenskonstrad.se","dns":-2,"web":3,"email":0,"total":1,"rank":130},{"name":"statensmedierad.se","dns":1,"web":4,"email":-1,"total":4,"rank":68},{"name":"statenssc.se","dns":2,"web":0,"email":0,"total":2,"rank":125},{"name":"stat-inst.se","dns":1,"web":3,"email":0,"total":4,"rank":69},{"name":"statskontoret.se","dns":2,"web":0,"email":2,"total":4,"rank":70},{"name":"stralsakerhetsmyndigheten.se","dns":1,"web":1,"email":-2,"total":0,"rank":161},{"name":"sva.se","dns":1,"web":-1,"email":1,"total":1,"rank":135},{"name":"svk.se","dns":2,"web":1,"email":0,"total":3,"rank":99},{"name":"swedac.se","dns":0,"web":0,"email":1,"total":1,"rank":137},{"name":"tillvaxtanalys.se","dns":1,"web":1,"email":-3,"total":-1,"rank":184},{"name":"tillvaxtverket.se","dns":2,"web":1,"email":2,"total":5,"rank":49},{"name":"tlv.se","dns":2,"web":4,"email":0,"total":6,"rank":34},{"name":"trafa.se","dns":1,"web":1,"email":2,"total":4,"rank":73},{"name":"trafikverket.se","dns":2,"web":5,"email":0,"total":7,"rank":20},{"name":"transportstyrelsen.se","dns":2,"web":-4,"email":0,"total":-2,"rank":188},{"name":"tullverket.se","dns":-1,"web":-1,"email":3,"total":1,"rank":142},{"name":"uhr.se","dns":0,"web":2,"email":3,"total":5,"rank":52},{"name":"uka.se","dns":-1,"web":4,"email":-3,"total":0,"rank":157},{"name":"undom.se","dns":1,"web":-2,"email":2,"total":1,"rank":144},{"name":"upphandlingsmyndigheten.se","dns":0,"web":-2,"email":0,"total":-2,"rank":189},{"name":"vardanalys.se","dns":0,"web":0,"email":1,"total":1,"rank":145},{"name":"varldskulturmuseerna.se","dns":1,"web":0,"email":2,"total":3,"rank":105},{"name":"vinnova.se","dns":2,"web":2,"email":0,"total":4,"rank":76},{"name":"vr.se","dns":2,"web":4,"email":0,"total":6,"rank":36},{"name":"vti.se","dns":1,"web":4,"email":2,"total":7,"rank":21},{"name":"brå.se","dns":1,"web":0,"email":3,"total":4,"rank":79},{"name":"försvarsmakten.se","dns":1,"web":0,"email":-1,"total":0,"rank":165},{"name":"konstnärsnämnden.se","dns":1,"web":0,"email":-1,"total":0,"rank":166},{"name":"kulturrådet.se","dns":2,"web":0,"email":0,"total":2,"rank":124},{"name":"läkemedelsverket.se","dns":1,"web":3,"email":0,"total":4,"rank":80},{"name":"naturvårdsverket.se","dns":2,"web":1,"email":2,"total":5,"rank":55},{"name":"sjöfartsverket.se","dns":1,"web":0,"email":0,"total":1,"rank":154},{"name":"språkochfolkminnen.se","dns":1,"web":0,"email":-2,"total":-1,"rank":182},{"name":"strålsäkerhetsmyndigheten.se","dns":1,"web":0,"email":0,"total":1,"rank":155},{"name":"tillväxtverket.se","dns":0,"web":0,"email":0,"total":0,"rank":172},{"name":"ukä.se","dns":-1,"web":0,"email":0,"total":-1,"rank":185},{"name":"vårdanalys.se","dns":0,"web":0,"email":-2,"total":-2,"rank":191}],"rank":9},{"name":"Statligt ägda bolag","id":"statligtgdabolag","dns":44,"web":74,"email":73,"total":191,"hosts":[{"name":"akademiskahus.se","dns":-1,"web":0,"email":2,"total":1,"rank":40},{"name":"almi.se","dns":1,"web":3,"email":0,"total":4,"rank":23},{"name":"apl.se","dns":0,"web":4,"email":2,"total":6,"rank":11},{"name":"apoteket.se","dns":1,"web":0,"email":0,"total":1,"rank":37},{"name":"arlandabananinfrastructure.se","dns":2,"web":1,"email":2,"total":5,"rank":17},{"name":"bilprovningen.se","dns":2,"web":4,"email":4,"total":10,"rank":3},{"name":"dramaten.se","dns":1,"web":3,"email":2,"total":6,"rank":12},{"name":"eurofima.org","dns":1,"web":-1,"email":0,"total":0,"rank":44},{"name":"gotakanal.se","dns":1,"web":4,"email":2,"total":7,"rank":8},{"name":"greencargo.se","dns":2,"web":-2,"email":1,"total":1,"rank":39},{"name":"industrifonden.se","dns":0,"web":3,"email":0,"total":3,"rank":29},{"name":"infranord.se","dns":2,"web":-2,"email":3,"total":3,"rank":30},{"name":"jernhusen.se","dns":2,"web":3,"email":3,"total":8,"rank":6},{"name":"lernia.se","dns":1,"web":1,"email":3,"total":5,"rank":14},{"name":"lkab.com","dns":2,"web":2,"email":-3,"total":1,"rank":42},{"name":"metria.se","dns":2,"web":3,"email":-1,"total":4,"rank":27},{"name":"norrlandsfonden.se","dns":1,"web":3,"email":2,"total":6,"rank":10},{"name":"operan.se","dns":1,"web":1,"email":3,"total":5,"rank":19},{"name":"orio.com","dns":1,"web":3,"email":3,"total":7,"rank":9},{"name":"postnord.se","dns":2,"web":-1,"email":0,"total":1,"rank":43},{"name":"ri.se","dns":2,"web":4,"email":3,"total":9,"rank":5},{"name":"samhall.se","dns":1,"web":2,"email":3,"total":6,"rank":13},{"name":"saminvest.se","dns":0,"web":3,"email":2,"total":5,"rank":20},{"name":"sas.se","dns":1,"web":6,"email":3,"total":10,"rank":2},{"name":"sbab.se","dns":0,"web":2,"email":1,"total":3,"rank":32},{"name":"sbo.se","dns":1,"web":1,"email":2,"total":4,"rank":26},{"name":"sek.se","dns":-2,"web":2,"email":1,"total":1,"rank":38},{"name":"sj.se","dns":1,"web":3,"email":1,"total":5,"rank":15},{"name":"sosalarm.se","dns":0,"web":1,"email":2,"total":3,"rank":31},{"name":"specialfastigheter.se","dns":0,"web":2,"email":3,"total":5,"rank":16},{"name":"sscspace.com","dns":1,"web":3,"email":3,"total":7,"rank":7},{"name":"svanen.se","dns":1,"web":-5,"email":0,"total":-4,"rank":47},{"name":"sveaskog.se","dns":1,"web":-2,"email":-1,"total":-2,"rank":46},{"name":"svedab.se","dns":1,"web":2,"email":2,"total":5,"rank":18},{"name":"svenskaskeppshypotek.se","dns":-1,"web":3,"email":2,"total":4,"rank":22},{"name":"svenskaspel.se","dns":2,"web":5,"email":2,"total":9,"rank":4},{"name":"svevia.se","dns":1,"web":-1,"email":3,"total":3,"rank":33},{"name":"swedavia.se","dns":1,"web":3,"email":0,"total":4,"rank":24},{"name":"swedfund.se","dns":1,"web":1,"email":2,"total":4,"rank":25},{"name":"systembolaget.se","dns":2,"web":6,"email":3,"total":11,"rank":1},{"name":"telia.se","dns":1,"web":2,"email":2,"total":5,"rank":21},{"name":"teracom.se","dns":-2,"web":-2,"email":2,"total":-2,"rank":45},{"name":"vasallen.se","dns":1,"web":1,"email":2,"total":4,"rank":28},{"name":"vattenfall.se","dns":1,"web":1,"email":1,"total":3,"rank":34},{"name":"visitsweden.com","dns":1,"web":1,"email":-1,"total":1,"rank":41},{"name":"voksenaasen.no","dns":2,"web":-2,"email":2,"total":2,"rank":35},{"name":"voksenaasen.se","dns":2,"web":0,"email":0,"total":2,"rank":36}],"rank":2},{"name":"Universitet och högskolor","id":"universitetochhgskolor","dns":51,"web":80,"email":72,"total":203,"hosts":[{"name":"altutbildning.se","dns":0,"web":3,"email":2,"total":5,"rank":19},{"name":"beckmans.se","dns":0,"web":3,"email":-1,"total":2,"rank":42},{"name":"bth.se","dns":2,"web":3,"email":2,"total":7,"rank":11},{"name":"cbti.se","dns":1,"web":0,"email":2,"total":3,"rank":36},{"name":"chalmers.se","dns":2,"web":1,"email":2,"total":5,"rank":18},{"name":"du.se","dns":2,"web":3,"email":3,"total":8,"rank":1},{"name":"ericastiftelsen.se","dns":1,"web":3,"email":2,"total":6,"rank":12},{"name":"esh.se","dns":1,"web":1,"email":-1,"total":1,"rank":44},{"name":"evidens4u.se","dns":2,"web":3,"email":2,"total":7,"rank":9},{"name":"fhs.se","dns":1,"web":1,"email":3,"total":5,"rank":22},{"name":"gammelkroppa.se","dns":1,"web":-3,"email":2,"total":0,"rank":46},{"name":"gih.se","dns":1,"web":1,"email":2,"total":4,"rank":28},{"name":"gu.se","dns":2,"web":4,"email":2,"total":8,"rank":2},{"name":"hb.se","dns":2,"web":3,"email":2,"total":7,"rank":5},{"name":"hh.se","dns":1,"web":2,"email":2,"total":5,"rank":20},{"name":"hhs.se","dns":-1,"web":4,"email":2,"total":5,"rank":21},{"name":"hig.se","dns":2,"web":-1,"email":2,"total":3,"rank":33},{"name":"his.se","dns":1,"web":4,"email":2,"total":7,"rank":6},{"name":"hkr.se","dns":0,"web":0,"email":2,"total":2,"rank":37},{"name":"hv.se","dns":1,"web":1,"email":0,"total":2,"rank":39},{"name":"johannelund.nu","dns":1,"web":0,"email":2,"total":3,"rank":31},{"name":"ju.se","dns":1,"web":1,"email":2,"total":4,"rank":23},{"name":"kau.se","dns":1,"web":4,"email":2,"total":7,"rank":7},{"name":"ki.se","dns":0,"web":-2,"email":2,"total":0,"rank":47},{"name":"kkh.se","dns":-1,"web":1,"email":2,"total":2,"rank":41},{"name":"kmh.se","dns":1,"web":4,"email":2,"total":7,"rank":8},{"name":"konstfack.se","dns":2,"web":2,"email":0,"total":4,"rank":27},{"name":"kth.se","dns":2,"web":1,"email":0,"total":3,"rank":34},{"name":"liu.se","dns":2,"web":5,"email":1,"total":8,"rank":3},{"name":"lnu.se","dns":1,"web":0,"email":2,"total":3,"rank":29},{"name":"ltu.se","dns":2,"web":1,"email":3,"total":6,"rank":15},{"name":"lu.se","dns":1,"web":-3,"email":1,"total":-1,"rank":48},{"name":"mau.se","dns":1,"web":1,"email":2,"total":4,"rank":24},{"name":"mdh.se","dns":1,"web":4,"email":2,"total":7,"rank":10},{"name":"miun.se","dns":1,"web":2,"email":0,"total":3,"rank":35},{"name":"newman.se","dns":1,"web":3,"email":2,"total":6,"rank":13},{"name":"oru.se","dns":1,"web":-1,"email":2,"total":2,"rank":38},{"name":"rkh.se","dns":1,"web":1,"email":-1,"total":1,"rank":43},{"name":"sapu.se","dns":1,"web":3,"email":2,"total":6,"rank":14},{"name":"shh.se","dns":0,"web":3,"email":0,"total":3,"rank":30},{"name":"sh.se","dns":2,"web":4,"email":2,"total":8,"rank":4},{"name":"slu.se","dns":1,"web":0,"email":2,"total":3,"rank":32},{"name":"smi.se","dns":1,"web":1,"email":2,"total":4,"rank":25},{"name":"su.se","dns":1,"web":4,"email":-1,"total":4,"rank":26},{"name":"ths.se","dns":0,"web":0,"email":2,"total":2,"rank":40},{"name":"umu.se","dns":2,"web":-1,"email":-1,"total":0,"rank":45},{"name":"uniarts.se","dns":1,"web":3,"email":2,"total":6,"rank":16},{"name":"uu.se","dns":1,"web":3,"email":2,"total":6,"rank":17}],"rank":1}]}